Workbook

Sheet Sales Data
A1: Order ID | B1: Order Date | C1: Customer Name | D1: Product | E1: Category | F1: Region | G1: Quantity | H1: Unit Price | I1: Revenue | J1: Cost
A2: ORD0001 | B2: 46085 | C2: Meena Joshi | D2: Smartphone | E2: Electronics | F2: South | G2: 1 | H2: 29352.68 | I2: 29352.68 | J2: =I2*75% -> 22014.51
A3: ORD0002 | B3: 46131 | C3: Priya Reddy | D3: Smartphone | E3: Electronics | F3: North | G3: 5 | H3: 25686.86 | I3: 128434.3 | J3: =I3*75% -> 96325.725
A4: ORD0003 | B4: 46177 | C4: Rahul Sharma | D4: Smartphone | E4: Electronics | F4: Central | G4: 2 | H4: 26502.9 | I4: 53005.8 | J4: =I4*75% -> 39754.35
A5: ORD0004 | B5: 46137 | C5: Nikhil Jain | D5: Monitor | E5: Electronics | F5: East | G5: 5 | H5: 14758.56 | I5: 73792.8 | J5: =I5*75% -> 55344.6
A6: ORD0005 | B6: 46110 | C6: Rohit Verma | D6: Laptop | E6: Electronics | F6: South | G6: 2 | H6: 57179.53 | I6: 114359.06 | J6: =I6*75% -> 85769.295
A7: ORD0006 | B7: 46120 | C7: Sneha Patel | D7: Monitor | E7: Electronics | F7: East | G7: 3 | H7: 13806.63 | I7: 41419.89 | J7: =I7*75% -> 31064.917
A8: ORD0007 | B8: 46034 | C8: Manoj Reddy | D8: Mouse | E8: Accessories | F8: Central | G8: 5 | H8: 857.61 | I8: 4288.05 | J8: =I8*75% -> 3216.0375
A9: ORD0008 | B9: 46098 | C9: Lakshmi Devi | D9: Smartphone | E9: Electronics | F9: East | G9: 4 | H9: 25641.28 | I9: 102565.12 | J9: =I9*75% -> 76923.84
A10: ORD0009 | B10: 46034 | C10: Meena Joshi | D10: Printer | E10: Electronics | F10: East | G10: 2 | H10: 12490.97 | I10: 24981.94 | J10: =I10*75% -> 18736.455
A11: ORD0010 | B11: 46120 | C11: Rohit Verma | D11: Smartphone | E11: Electronics | F11: West | G11: 2 | H11: 30052.31 | I11: 60104.62 | J11: =I11*75% -> 45078.465
A12: ORD0011 | B12: 46076 | C12: Rohit Verma | D12: Mouse | E12: Accessories | F12: North | G12: 2 | H12: 876.63 | I12: 1753.26 | J12: =I12*75% -> 1314.945
A13: ORD0012 | B13: 46085 | C13: Ananya Rao | D13: Printer | E13: Electronics | F13: West | G13: 2 | H13: 12081.94 | I13: 24163.88 | J13: =I13*75% -> 18122.91
... A121: ORD0120 | B121: 46235 | C121: Manoj Reddy | D121: Office Chair | E121: Furniture | F121: South | G121: 3 | H121: 8730.49 | I121: 26191.47 | J121: =I121*75% -> 19643.603

Sheet Basic Formulas & Calculations
A1: Sum | B1: Total Quantity | C1: Total Unit Price | D1: Total Revenue
B2: =SUM('Sales Data'!$G:$G) -> 348 | C2: =SUM('Sales Data'!H:H) -> 1742170.8 | D2: =SUM('Sales Data'!I:I) -> 5053724.5
A4: Average | B4: Average Quantity | C4: Average Unit Price | D4: Average Revenue
B5: =AVERAGE('Sales Data'!G:G) -> 2.9 | C5: =AVERAGE('Sales Data'!H:H) -> 14518.09 | D5: =AVERAGE('Sales Data'!I:I) -> 42114.371
A7: Count | B7: Total Orders
B8: =COUNT('Sales Data'!B:B) -> 120
A10: CountA | B10: Customer Entries
B11: =COUNTA('Sales Data'!C:C)-1 -> 120
A13: Max | B13: Max Quantity | C13: Max Unit Price | D13: Max Revenue
B14: =MAX('Sales Data'!G:G) -> 5 | C14: =MAX('Sales Data'!H:H) -> 59147.42 | D14: =MAX('Sales Data'!I:I) -> 277965.7
A16: Min | B16: Min Quantity | C16: Min Unit Price | D16: Min Revenue
B17: =+MIN('Sales Data'!G:G) -> 1 | C17: =MIN('Sales Data'!H:H) -> 851.23 | D17: =MIN('Sales Data'!I:I) -> 851.23

Sheet Conditional Formulas
A1: Countif | B1: How many Electronics orders?
B2: =COUNTIF('Sales Data'!E:E,"Electronics") -> 63
A5: Countifs | B5: How many Electronic orders in South Region
B6: =COUNTIFS('Sales Data'!E:E,"Electronics",'Sales Data'!F:F,"South") -> 14
A8: Sumif | B8: Revenue from Electronics?
B9: =SUMIF('Sales Data'!E:E,"Electronics",'Sales Data'!I:I) -> 4142688.1
A12: Sumifs | B12: Revenue from South Electronics?
B13: =SUMIFS('Sales Data'!I:I,'Sales Data'!E:E,"Electronics",'Sales Data'!F:F,"South") -> 955804.06
A16: Averageif | B16: Average revenue from Electronics?
B17: =AVERAGEIF('Sales Data'!E:E,"Electronics",'Sales Data'!I:I) -> 65756.955
A20: Averageifs | B20: Average revenue from South Electronics?
B21: =AVERAGEIFS('Sales Data'!I:I,'Sales Data'!E:E,"Electronics",'Sales Data'!F:F,"South") -> 68271.719

Sheet Revenue Calculations
A1: Revenue By Products | E1: Revenue By Category | I1: Revenue By Region
A3: {=_xlfn.UNIQUE('Sales Data'!D:D)} -> Product | B3: Revenue | E3: {=_xlfn.UNIQUE('Sales Data'!E:E)} -> Category | F3: Revenue | I3: {=_xlfn.UNIQUE('Sales Data'!F:F)} -> Region | J3: Revenue
A4: Smartphone | B4: =SUMIF('Sales Data'!D:D,A4,'Sales Data'!I:I) -> 1255308.1 | E4: Electronics | F4: =SUMIF('Sales Data'!E:E,'Revenue Calculations'!E4,'Sales Data'!I:I) -> 4142688.1 | I4: South | J4: =SUMIF('Sales Data'!F:F,'Revenue Calculations'!I4,'Sales Data'!I:I) -> 1149852.7
A5: Monitor | B5: =SUMIF('Sales Data'!D:D,A5,'Sales Data'!I:I) -> 703898.44 | E5: Accessories | F5: =SUMIF('Sales Data'!E:E,'Revenue Calculations'!E5,'Sales Data'!I:I) -> 146219.74 | I5: North | J5: =SUMIF('Sales Data'!F:F,'Revenue Calculations'!I5,'Sales Data'!I:I) -> 963973.39
A6: Laptop | B6: =SUMIF('Sales Data'!D:D,A6,'Sales Data'!I:I) -> 1714537.9 | E6: Furniture | F6: =SUMIF('Sales Data'!E:E,'Revenue Calculations'!E6,'Sales Data'!I:I) -> 764816.66 | I6: Central | J6: =SUMIF('Sales Data'!F:F,'Revenue Calculations'!I6,'Sales Data'!I:I) -> 794071.59
A7: Mouse | B7: =SUMIF('Sales Data'!D:D,A7,'Sales Data'!I:I) -> 14150.97 | E7: 0 | I7: East | J7: =SUMIF('Sales Data'!F:F,'Revenue Calculations'!I7,'Sales Data'!I:I) -> 1177426.3
A8: Printer | B8: =SUMIF('Sales Data'!D:D,A8,'Sales Data'!I:I) -> 390252.37 | I8: West | J8: =SUMIF('Sales Data'!F:F,'Revenue Calculations'!I8,'Sales Data'!I:I) -> 968400.49
A9: Office Chair | B9: =SUMIF('Sales Data'!D:D,A9,'Sales Data'!I:I) -> 409784.07 | I9: 0
A10: Keyboard | B10: =SUMIF('Sales Data'!D:D,A10,'Sales Data'!I:I) -> 67211.28
A11: Headphones | B11: =SUMIF('Sales Data'!D:D,A11,'Sales Data'!I:I) -> 78691.27
A12: Backpack | B12: =SUMIF('Sales Data'!D:D,A12,'Sales Data'!I:I) -> 64857.49
A13: Desk | B13: =SUMIF('Sales Data'!D:D,A13,'Sales Data'!I:I) -> 355032.59
A14: 0

Sheet Creating Profit&Profit Margin  
A1: Order ID | B1: Order Date | C1: Customer Name | D1: Product | E1: Category | F1: Region | G1: Quantity | H1: Unit Price | I1: Revenue | J1: Cost | K1: Profit | L1: Profit Margin
A2: ORD0001 | B2: 46085 | C2: Meena Joshi | D2: Smartphone | E2: Electronics | F2: South | G2: 1 | H2: 29352.68 | I2: 29352.68 | J2: =I2*75% -> 22014.51 | K2: =I2-J2 -> 7338.17 | L2: =K2/I2 -> 0.25
A3: ORD0002 | B3: 46131 | C3: Priya Reddy | D3: Smartphone | E3: Electronics | F3: North | G3: 5 | H3: 25686.86 | I3: 128434.3 | J3: =I3*75% -> 96325.725 | K3: =I3-J3 -> 32108.575 | L3: =K3/I3 -> 0.25
A4: ORD0003 | B4: 46177 | C4: Rahul Sharma | D4: Smartphone | E4: Electronics | F4: Central | G4: 2 | H4: 26502.9 | I4: 53005.8 | J4: =I4*75% -> 39754.35 | K4: =I4-J4 -> 13251.45 | L4: =K4/I4 -> 0.25
A5: ORD0004 | B5: 46137 | C5: Nikhil Jain | D5: Monitor | E5: Electronics | F5: East | G5: 5 | H5: 14758.56 | I5: 73792.8 | J5: =I5*75% -> 55344.6 | K5: =I5-J5 -> 18448.2 | L5: =K5/I5 -> 0.25
A6: ORD0005 | B6: 46110 | C6: Rohit Verma | D6: Laptop | E6: Electronics | F6: South | G6: 2 | H6: 57179.53 | I6: 114359.06 | J6: =I6*75% -> 85769.295 | K6: =I6-J6 -> 28589.765 | L6: =K6/I6 -> 0.25
A7: ORD0006 | B7: 46120 | C7: Sneha Patel | D7: Monitor | E7: Electronics | F7: East | G7: 3 | H7: 13806.63 | I7: 41419.89 | J7: =I7*75% -> 31064.917 | K7: =I7-J7 -> 10354.972 | L7: =K7/I7 -> 0.25
A8: ORD0007 | B8: 46034 | C8: Manoj Reddy | D8: Mouse | E8: Accessories | F8: Central | G8: 5 | H8: 857.61 | I8: 4288.05 | J8: =I8*75% -> 3216.0375 | K8: =I8-J8 -> 1072.0125 | L8: =K8/I8 -> 0.25
A9: ORD0008 | B9: 46098 | C9: Lakshmi Devi | D9: Smartphone | E9: Electronics | F9: East | G9: 4 | H9: 25641.28 | I9: 102565.12 | J9: =I9*75% -> 76923.84 | K9: =I9-J9 -> 25641.28 | L9: =K9/I9 -> 0.25
A10: ORD0009 | B10: 46034 | C10: Meena Joshi | D10: Printer | E10: Electronics | F10: East | G10: 2 | H10: 12490.97 | I10: 24981.94 | J10: =I10*75% -> 18736.455 | K10: =I10-J10 -> 6245.485 | L10: =K10/I10 -> 0.25
A11: ORD0010 | B11: 46120 | C11: Rohit Verma | D11: Smartphone | E11: Electronics | F11: West | G11: 2 | H11: 30052.31 | I11: 60104.62 | J11: =I11*75% -> 45078.465 | K11: =I11-J11 -> 15026.155 | L11: =K11/I11 -> 0.25
A12: ORD0011 | B12: 46076 | C12: Rohit Verma | D12: Mouse | E12: Accessories | F12: North | G12: 2 | H12: 876.63 | I12: 1753.26 | J12: =I12*75% -> 1314.945 | K12: =I12-J12 -> 438.315 | L12: =K12/I12 -> 0.25
A13: ORD0012 | B13: 46085 | C13: Ananya Rao | D13: Printer | E13: Electronics | F13: West | G13: 2 | H13: 12081.94 | I13: 24163.88 | J13: =I13*75% -> 18122.91 | K13: =I13-J13 -> 6040.97 | L13: =K13/I13 -> 0.25
... A121: ORD0120 | B121: 46235 | C121: Manoj Reddy | D121: Office Chair | E121: Furniture | F121: South | G121: 3 | H121: 8730.49 | I121: 26191.47 | J121: =I121*75% -> 19643.603 | K121: =I121-J121 -> 6547.8675 | L121: =K121/I121 -> 0.25

Sheet IF,NESTED IF,AND,OR
A1: IF | B1: =IF('Sales Data'!I2<15000,"Low-Value","Medium-Value") -> Medium-Value | C1: Used when there is one condition
A3: NESTEDIF | B3: =IF('Sales Data'!I2>=50000,"High-Value",IF('Sales Data'!I2<15000,"Low-Value","Medium-Value")) -> Medium-Value | C3: Used when there is more then one condition
A5: AND | B5: =IF(AND('Sales Data'!I2>=50000,'Sales Data'!L2>=20%),"Strong","Not Strong") -> Not Strong | C5: To check both conditions are true or not
A7: OR | B7: =IF(OR('Sales Data'!I2<15000,'Sales Data'!L2>15%),"Poor","Not Poor") -> Not Poor | C7: To check either one condition is true or not

Sheet Findings
A1: S.No. | B1: Findings
A2: 1 | B2: The dataset contains 120 orders. | C2: =COUNTA('Sales Data'!A:A)-1 -> 120
A3: 2 | B3: Total quantity sold is 348 units. | C3: =SUM('Sales Data'!G:G) -> 348
A4: 3 | B4: Total revenue is 50,53,724.54. | C4: =SUM('Sales Data'!I:I) -> 5053724.5
A5: 4 | B5: Average order value is 42,114.37. | C5: =AVERAGE('Sales Data'!I:I) -> 42114.371
A6: 5 | B6: Minimum order value is 851.23. | C6: =MIN('Sales Data'!I:I) -> 851.23
A7: 6 | B7: Maximum order value is 2,77,965.70. | C7: =MAX('Sales Data'!I:I) -> 277965.7
A8: 7 | B8: Laptop generates the highest product revenue (17,14,537.95). | C8: =MAX('Revenue Calculations'!B:B) -> 1714537.9
A9: 8 | B9: Electronics generates the highest category revenue (41,42,688.14). | C9: =MAX('Revenue Calculations'!F:F) -> 4142688.1
A10: 9 | B10: East generates the highest regional revenue (11,77,426.33). | C10: =MAX('Revenue Calculations'!J:J) -> 1177426.3
A11: 10 | B11: The Total Proift is 12,63,431 | C11: =SUM('Creating Profit&Profit Margin '!K:K) -> 1263431.1
