Workbook
Name Slicer_Category: #N/A
Name Slicer_Months__Order_Date: #N/A
Name Slicer_Product: #N/A
Name Slicer_Region: #N/A

Sheet RawData
A1: Order_ID | B1: Order_Date | C1: Region | D1: City | E1: Product | F1: Category | G1: Quantity | H1: Unit_Price | I1: Discount | J1: Revenue | K1: Cost | L1: Profit
A2: ORD0001 | B2: 45985 | C2: North | D2: Delhi | E2: Laptop | F2: Electronics | G2: 5 | H2: 818.01 | I2: 0.02 | J2: 4008.25 | K2: 3233.43 | L2: 774.82
A3: ORD0002 | B3: 45729 | C3: North | D3: Lucknow | E3: Backpack | F3: Accessories | G3: 9 | H3: 48.13 | I3: 0 | J3: 433.17 | K3: 308.26 | L3: 124.91
A4: ORD0003 | B4: 45874 | C4: North | D4: Delhi | E4: Laptop | F4: Electronics | G4: 2 | H4: 762.28 | I4: 0.02 | J4: 1494.07 | K4: 884.67 | L4: 609.4
A5: ORD0004 | B5: 45916 | C5: North | D5: Lucknow | E5: Notebook | F5: Office Supplies | G5: 4 | H5: 6.94 | I5: 0.2 | J5: 22.21 | K5: 17.41 | L5: 4.8
A6: ORD0005 | B6: 46017 | C6: West | D6: Pune | E6: Monitor | F6: Electronics | G6: 8 | H6: 226.67 | I6: 0.15 | J6: 1541.36 | K6: 1142.42 | L6: 398.94
A7: ORD0006 | B7: 45661 | C7: South | D7: Chennai | E7: Keyboard | F7: Accessories | G7: 7 | H7: 29.97 | I7: 0.05 | J7: 199.3 | K7: 161.81 | L7: 37.49
A8: ORD0007 | B8: 45737 | C8: South | D8: Chennai | E8: Desk | F8: Furniture | G8: 2 | H8: 274.93 | I8: 0 | J8: 549.86 | K8: 333.95 | L8: 215.91
A9: ORD0008 | B9: 45707 | C9: East | D9: Hyderabad | E9: Desk | F9: Furniture | G9: 10 | H9: 226.14 | I9: 0.05 | J9: 2148.33 | K9: 1287.97 | L9: 860.36
A10: ORD0009 | B10: 45893 | C10: North | D10: Jaipur | E10: Bookshelf | F10: Furniture | G10: 2 | H10: 131.78 | I10: 0.15 | J10: 224.03 | K10: 154.96 | L10: 69.07
A11: ORD0010 | B11: 45979 | C11: East | D11: Kolkata | E11: Pen Set | F11: Office Supplies | G11: 4 | H11: 11.76 | I11: 0.2 | J11: 37.63 | K11: 23.66 | L11: 13.97
A12: ORD0011 | B12: 45681 | C12: South | D12: Hyderabad | E12: Office Chair | F12: Furniture | G12: 2 | H12: 186.04 | I12: 0.02 | J12: 364.64 | K12: 214.29 | L12: 150.35
A13: ORD0012 | B13: 45852 | C13: East | D13: Bhubaneswar | E13: Printer | F13: Office Supplies | G13: 6 | H13: 150.02 | I13: 0.02 | J13: 882.12 | K13: 572.42 | L13: 309.7
... A52: ORD0051 | B52: 45687 | C52: North | D52: Delhi | E52: Keyboard | F52: Accessories | G52: 6 | H52: 30.08 | I52: 0 | J52: 180.48 | K52: 130.28 | L52: 50.2
A53: ORD0052 | B53: 45957 | C53: West | D53: Mumbai | E53: Notebook | F53: Office Supplies | H53: 7.55 | I53: 0.02 | J53: 66.59 | K53: 45.77 | L53: 20.82
A54: ORD0053 | B54: 45918 | C54: North | D54: Delhi | E54: Headphones | F54: Electronics | G54: 2 | H54: 89.78 | I54: 0.15 | J54: 152.63 | K54: 94.22 | L54: 58.41
A55: ORD0054 | B55: 46003 | C55: South | D55: Hyderabad | E55: Bookshelf | F55: Furniture | G55: 2 | H55: 136.24 | I55: 0.15 | J55: 231.61 | K55: 174.63 | L55: 56.98
A56: ORD0055 | B56: 45954 | C56: North | D56: Lucknow | E56: Pen Set | F56: Office Supplies | G56: 2 | H56: 11.02 | I56: 0.1 | J56: 19.84 | K56: 11.32 | L56: 8.52
A57: ORD0056 | B57: 45956 | C57: East | D57: Patna | E57: Office Chair | F57: Furniture | G57: 4 | H57: 168.65 | I57: 0.2 | J57: 539.68 | K57: 320.32 | L57: 219.36
A58: ORD0057 | B58: 45818 | C58: South | D58: Bengaluru | E58: Office Chair | F58: Furniture | G58: 7 | H58: 203.2 | I58: 0.02 | J58: 1393.95 | K58: 1070.82 | L58: 323.13
A59: ORD0058 | B59: 45988 | C59: East | D59: Kolkata | E59: Printer | F59: Office Supplies | G59: 6 | H59: 166.4 | I59: 0 | J59: 998.4 | K59: 784.04 | L59: 214.36
A60: ORD0059 | B60: 45892 | C60: North | D60: Lucknow | E60: Smartphone | F60: Electronics | G60: 9 | H60: 600.11 | I60: 0.02 | J60: 5292.97 | K60: 3177.76 | L60: 2115.21
A61: ORD0060 | B61: 45793 | C61: South | D61: Chennai | E61: Desk | F61: Furniture | G61: 2 | H61: 279.44 | I61: 0.02 | J61: 547.7 | K61: 380.99 | L61: 166.71
A62: ORD0061 | B62: 45803 | C62: South | D62: Chennai | E62: Printer | F62: Office Supplies | G62: 9 | H62: 174.76 | I62: 0.2 | J62: 1258.27 | K62: 996.48 | L62: 261.79
A63: ORD0062 | B63: 45971 | C63: North | D63: Lucknow | E63: Backpack | F63: Accessories | G63: 9 | H63: 42.54 | I63: 0.05 | J63: 363.72 | K63: 210.85 | L63: 152.87
A64: ORD0063 | B64: 45711 | C64: South | D64: Bengaluru | E64: Office Chair | F64: Furniture | G64: 2 | H64: 165.31 | I64: 0 | J64: 330.62 | K64: 219.97 | L64: 110.65
A65: ORD0064 | B65: 45941 | C65: South | D65: Hyderabad | E65: Office Chair | F65: Furniture | G65: 5 | H65: 197.17 | I65: 0.15 | J65: 837.97 | K65: 655.63 | L65: 182.34
... A69: ORD0068 | B69: 45884 | C69: West | D69: Mumbai | E69: Notebook | F69: Office Supplies | G69: 1 | H69: 9.06 | I69: 0 | J69: 9.06 | K69: 5.77 | L69: 3.29
A70: ORD0069 | B70: 46011 | C70: South | D70: Bengaluru | E70: Notebook | F70: Office Supplies | G70: 1 | H70: 8.05 | J70: 7.65 | K70: 5.66 | L70: 1.99
A71: ORD0070 | B71: 45940 | C71: South | D71: Chennai | E71: Bookshelf | F71: Furniture | G71: 3 | H71: 134.27 | I71: 0 | J71: 402.81 | K71: 327.24 | L71: 75.57
A72: ORD0071 | B72: 45844 | C72: North | D72: Delhi | E72: Desk | F72: Furniture | G72: 4 | H72: 284.68 | I72: 0.2 | J72: 910.98 | K72: 562.97 | L72: 348.01
A73: ORD0072 | B73: 45999 | C73: North | D73: Lucknow | E73: Desk | F73: Furniture | G73: 9 | H73: 249.79 | I73: 0.1 | J73: 2023.3 | K73: 1277.18 | L73: 746.12
A74: ORD0073 | B74: 45737 | C74: South | D74: Hyderabad | E74: Headphones | F74: Electronics | G74: 3 | H74: 74.84 | I74: 0.1 | J74: 202.07 | K74: 113.15 | L74: 88.92
A75: ORD0074 | B75: 45749 | C75: East | D75: Kolkata | E75: Bookshelf | F75: Furniture | G75: 4 | H75: 144.6 | I75: 0.05 | J75: 549.48 | K75: 376.79 | L75: 172.69
A76: ORD0075 | B76: 46017 | C76: North | D76: Delhi | E76: Bookshelf | F76: Furniture | G76: 1 | H76: 121.16 | I76: 0.1 | J76: 109.04 | K76: 68.18 | L76: 40.86
A77: ORD0076 | B77: 45760 | C77: West | D77: Mumbai | E77: Desk | F77: Furniture | G77: 5 | H77: 280.62 | I77: 0.02 | J77: 1375.04 | K77: 845.21 | L77: 529.83
A78: ORD0077 | B78: 45670 | C78: South | D78: Hyderabad | E78: Bookshelf | F78: Furniture | G78: 6 | H78: 125.09 | I78: 0.05 | J78: 713.01 | K78: 486.38 | L78: 226.63
A79: ORD0078 | B79: 45800 | C79: East | D79: Patna | E79: Backpack | F79: Accessories | G79: 9 | H79: 51.56 | I79: 0.1 | J79: 417.64 | K79: 257 | L79: 160.64
A80: ORD0079 | B80: 45932 | C80: East | D80: Kolkata | E80: Laptop | F80: Electronics | G80: 2 | H80: 893.89 | I80: 0.05 | J80: 1698.39 | K80: 1283.37 | L80: 415.02
A81: ORD0080 | B81: 45955 | C81: East | D81: Bhubaneswar | E81: Laptop | F81: Electronics | G81: 2 | H81: 783.1 | I81: 0.15 | J81: 1331.27 | K81: 993.95 | L81: 337.32
A82: ORD0081 | B82: 45834 | C82: East | D82: Kolkata | E82: Bookshelf | F82: Furniture | G82: 10 | H82: 134.45 | I82: 0.15 | J82: 1142.83 | K82: 823.66 | L82: 319.17
... A84: ORD0083 | B84: 45658 | C84: South | D84: Bengaluru | E84: Desk | F84: Furniture | G84: 7 | H84: 219.27 | I84: 0 | J84: 1534.89 | K84: 1190.36 | L84: 344.53
A85: ORD0084 | B85: 45827 | C85: East | D85: Bhubaneswar | E85: Backpack | F85: Accessories | G85: 2 | I85: 0.2 | J85: 68.13 | K85: 40.9 | L85: 27.23
A86: ORD0085 | B86: 45917 | C86: East | D86: Bhubaneswar | E86: Backpack | F86: Accessories | G86: 7 | H86: 38.8 | I86: 0.05 | J86: 258.02 | K86: 183.08 | L86: 74.94
A87: ORD0086 | B87: 46014 | C87: East | D87: Bhubaneswar | E87: Notebook | F87: Office Supplies | G87: 3 | H87: 8.43 | I87: 0.02 | J87: 24.78 | K87: 13.74 | L87: 11.04
A88: ORD0087 | B88: 45998 | C88: West | D88: Ahmedabad | E88: Backpack | F88: Accessories | G88: 3 | H88: 45.16 | I88: 0.15 | J88: 115.16 | K88: 70.38 | L88: 44.78
A89: ORD0088 | B89: 45812 | C89: West | D89: Pune | E89: Notebook | F89: Office Supplies | G89: 1 | H89: 8.35 | I89: 0.05 | J89: 7.93 | K89: 4.73 | L89: 3.2
A90: ORD0089 | B90: 45765 | C90: West | D90: Pune | E90: Pen Set | F90: Office Supplies | G90: 10 | H90: 12.69 | I90: 0.2 | J90: 101.52 | K90: 66.44 | L90: 35.08
A91: ORD0090 | B91: 45896 | C91: West | D91: Pune | E91: Printer | F91: Office Supplies | G91: 4 | H91: 180.96 | I91: 0.15 | J91: 615.26 | K91: 361.24 | L91: 254.02
A92: ORD0091 | B92: 45744 | C92: North | D92: Lucknow | E92: Office Chair | F92: Furniture | G92: 9 | H92: 171.42 | I92: 0.2 | J92: 1234.22 | K92: 716.63 | L92: 517.59
A93: ORD0092 | B93: 45975 | C93: East | D93: Bhubaneswar | E93: Smartphone | F93: Electronics | G93: 4 | H93: 620.07 | I93: 0.2 | J93: 1984.22 | K93: 1561.35 | L93: 422.87
A94: ORD0093 | B94: 45773 | C94: South | D94: Hyderabad | E94: Headphones | F94: Electronics | G94: 1 | H94: 74.19 | I94: 0 | J94: 74.19 | K94: 54.02 | L94: 20.17
A95: ORD0094 | B95: 45901 | C95: North | D95: Lucknow | E95: Printer | F95: Office Supplies | G95: 7 | H95: 175.23 | I95: 0.2 | J95: 981.29 | K95: 686.81 | L95: 294.48
A96: ORD0095 | B96: 45757 | C96: West | D96: Mumbai | E96: Printer | F96: Office Supplies | G96: 7 | H96: 161.42 | I96: 0.02 | J96: 1107.34 | K96: 681.35 | L96: 425.99
A97: ORD0096 | B97: 45993 | C97: North | D97: Delhi | E97: Smartphone | F97: Electronics | G97: 7 | H97: 482.86 | I97: 0.02 | J97: 3312.42 | K97: 2624.26 | L97: 688.16
... A222: ORD0221 | B222: 45708 | C222: West | D222: Mumbai | E222: Pen Set | F222: Office Supplies | G222: 7 | H222: 10.51 | I222: 0.05 | J222: 69.89 | K222: 57.06 | L222: 12.83
A223: ORD0222 | B223: 46011 | C223: East | D223: Kolkata | E223: Monitor | F223: Electronics | G223: 8 | H223: 211.7 | I223: 0.1 | K223: 990.87 | L223: 533.37
A224: ORD0223 | B224: 45843 | C224: North | D224: Lucknow | E224: Backpack | F224: Accessories | G224: 6 | H224: 49.22 | I224: 0.15 | J224: 251.02 | K224: 202.26 | L224: 48.76
A225: ORD0224 | B225: 45841 | C225: North | D225: Delhi | E225: Bookshelf | F225: Furniture | G225: 5 | H225: 160.41 | I225: 0.02 | J225: 786.01 | K225: 592.19 | L225: 193.82
A226: ORD0225 | B226: 45890 | C226: North | D226: Lucknow | E226: Backpack | F226: Accessories | G226: 4 | H226: 43.33 | I226: 0.2 | J226: 138.66 | K226: 79.39 | L226: 59.27
A227: ORD0226 | B227: 45963 | C227: North | D227: Delhi | E227: Laptop | F227: Electronics | G227: 6 | H227: 920.67 | I227: 0.02 | J227: 5413.54 | K227: 3793.64 | L227: 1619.9
A228: ORD0227 | B228: 45947 | C228: South | D228: Bengaluru | E228: Smartphone | F228: Electronics | G228: 9 | H228: 537.5 | I228: 0.02 | J228: 4740.75 | K228: 3767.55 | L228: 973.2
A229: ORD0228 | B229: 45768 | C229: South | D229: Hyderabad | E229: Desk | F229: Furniture | G229: 3 | H229: 220.84 | I229: 0.15 | J229: 563.14 | K229: 384.63 | L229: 178.51
A230: ORD0229 | B230: 45799 | C230: South | D230: Hyderabad | E230: Headphones | F230: Electronics | G230: 9 | H230: 68.27 | I230: 0.05 | J230: 583.71 | K230: 394.9 | L230: 188.81
A231: ORD0230 | B231: 45714 | C231: North | D231: Delhi | E231: Headphones | F231: Electronics | G231: 1 | H231: 69.35 | I231: 0.05 | J231: 65.88 | K231: 38.35 | L231: 27.53
A232: ORD0231 | B232: 45959 | C232: East | D232: Kolkata | E232: Laptop | F232: Electronics | G232: 3 | H232: 752.47 | I232: 0.05 | J232: 2144.54 | K232: 1555.41 | L232: 589.13
A233: ORD0232 | B233: 45722 | C233: West | D233: Mumbai | E233: Notebook | F233: Office Supplies | G233: 2 | H233: 8.59 | I233: 0.2 | J233: 13.74 | K233: 9.72 | L233: 4.02
A234: ORD0233 | B234: 45901 | C234: West | D234: Mumbai | E234: Desk | F234: Furniture | G234: 9 | H234: 284.66 | I234: 0.15 | J234: 2177.65 | K234: 1418.12 | L234: 759.53
A235: ORD0234 | B235: 45889 | C235: South | D235: Bengaluru | E235: Pen Set | F235: Office Supplies | G235: 1 | H235: 11.23 | I235: 0.2 | J235: 8.98 | K235: 7.05 | L235: 1.93
... A549: ORD0548 | B549: 45770 | C549: East | D549: Patna | E549: Laptop | F549: Electronics | G549: 5 | H549: 781.32 | I549: 0.02 | J549: 3828.47 | K549: 2288.13 | L549: 1540.34
A550: ORD0549 | B550: 45805 | C550: South | D550: Chennai | E550: Printer | F550: Office Supplies | H550: 146.58 | I550: 0.2 | J550: 1172.64 | K550: 703.98 | L550: 468.66
A551: ORD0550 | B551: 45939 | C551: North | D551: Lucknow | E551: Pen Set | F551: Office Supplies | G551: 2 | H551: 13.01 | I551: 0.05 | J551: 24.72 | K551: 15.93 | L551: 8.79
A552: ORD0551 | B552: 45845 | C552: North | D552: Delhi | E552: Keyboard | F552: Accessories | G552: 8 | H552: 30.36 | I552: 0.15 | J552: 206.45 | K552: 167.57 | L552: 38.88
A553: ORD0552 | B553: 45875 | C553: North | D553: Delhi | E553: Keyboard | F553: Accessories | G553: 4 | H553: 39.03 | I553: 0.05 | J553: 148.31 | K553: 118.72 | L553: 29.59
A554: ORD0553 | B554: 45888 | C554: East | D554: Kolkata | E554: Desk | F554: Furniture | G554: 2 | H554: 287.12 | I554: 0.1 | J554: 516.82 | K554: 308.52 | L554: 208.3
A555: ORD0554 | B555: 45779 | C555: South | D555: Chennai | E555: Keyboard | F555: Accessories | G555: 10 | H555: 33.91 | I555: 0.2 | J555: 271.28 | K555: 204.74 | L555: 66.54
A556: ORD0555 | B556: 46021 | C556: West | D556: Mumbai | E556: Headphones | F556: Electronics | G556: 10 | H556: 84.7 | I556: 0.02 | J556: 830.06 | K556: 491.02 | L556: 339.04
A557: ORD0556 | B557: 45763 | C557: North | D557: Jaipur | E557: Pen Set | F557: Office Supplies | G557: 6 | H557: 13.14 | I557: 0.15 | J557: 67.01 | K557: 40.92 | L557: 26.09
A558: ORD0557 | B558: 45963 | C558: South | D558: Bengaluru | E558: Desk | F558: Furniture | G558: 5 | H558: 229.29 | I558: 0.05 | J558: 1089.13 | K558: 756.93 | L558: 332.2
A559: ORD0558 | B559: 45794 | C559: North | D559: Jaipur | E559: Headphones | F559: Electronics | G559: 7 | H559: 82.23 | I559: 0 | J559: 575.61 | K559: 406.74 | L559: 168.87
A560: ORD0559 | B560: 45993 | C560: South | D560: Hyderabad | E560: Keyboard | F560: Accessories | G560: 3 | H560: 30.71 | I560: 0.02 | J560: 90.29 | K560: 71.05 | L560: 19.24
A561: ORD0560 | B561: 46022 | C561: East | D561: Kolkata | E561: Monitor | F561: Electronics | G561: 7 | H561: 204.53 | I561: 0.1 | J561: 1288.54 | K561: 753.76 | L561: 534.78
A562: ORD0561 | B562: 45953 | C562: East | D562: Bhubaneswar | E562: Backpack | F562: Accessories | G562: 7 | H562: 50.25 | I562: 0.1 | J562: 316.57 | K562: 255.8 | L562: 60.77
... A604: ORD0251 | B604: 45945 | C604: North | D604: Delhi | E604: Pen Set | F604: Office Supplies | G604: 5 | H604: 12.71 | I604: 0 | J604: 63.55 | K604: 44.15 | L604: 19.4

Sheet Cleaned Data
A1: Order_ID | B1: Order_Date | C1: Region | D1: City | E1: Product | F1: Category | G1: Quantity | H1: Unit_Price | I1: Discount | J1: Revenue | K1: Cost | L1: Profit
A2: ORD0001 | B2: 45985 | C2: =IF(RawData!C2="","Unknown",PROPER(TRIM(CLEAN(SUBSTITUTE(RawData!C2,CHAR(160)," "))))) -> North | D2: =IF(RawData!D2="","Unknown",PROPER(TRIM(CLEAN(SUBSTITUTE(RawData!D2,CHAR(160)," "))))) -> Delhi | E2: =IF(RawData!E2="","Unknown",PROPER(TRIM(CLEAN(SUBSTITUTE(RawData!E2,CHAR(160)," "))))) -> Laptop | F2: =IF(RawData!F2="","Unknown",PROPER(TRIM(CLEAN(SUBSTITUTE(RawData!F2,CHAR(160)," "))))) -> Electronics | G2: =_xlfn.LET( _xlpm.q,RawData!G2, _xlpm.u,RawData!H2, _xlpm.d,RawData!I2, _xlpm.r,RawData!J2, IF(AND(ISNUMBER(_xlpm.q),_xlpm.q>0),_xlpm.q, IF(AND(ISNUMBER(_xlpm.r),ISNUMBER(_xlpm.u),_xlpm.u>0,ISNUMBER(_xlpm.d),_xlpm.d>=0,_xlpm.d<1), ROUND(_xlpm.r/(_xlpm.u*(1-_xlpm.d)),0), "" ) ) ) -> 5 | H2: =_xlfn.LET( _xlpm.q,RawData!G2, _xlpm.u,RawData!H2, _xlpm.d,RawData!I2, _xlpm.r,RawData!J2, IF(AND(ISNUMBER(_xlpm.u),_xlpm.u>0),_xlpm.u, IF(AND(ISNUMBER(_xlpm.q),_xlpm.q>0,ISNUMBER(_xlpm.r),ISNUMBER(_xlpm.d),_xlpm.d>=0,_xlpm.d<1), _xlpm.r/(_xlpm.q*(1-_xlpm.d)), "" ) ) ) -> 818.01 | I2: =_xlfn.LET( _xlpm.q,RawData!G2, _xlpm.u,RawData!H2, _xlpm.d,RawData!I2, _xlpm.r,RawData!J2, IF(AND(ISNUMBER(_xlpm.d),_xlpm.d>=0,_xlpm.d<1),_xlpm.d, IF(AND(ISNUMBER(_xlpm.q),_xlpm.q>0,ISNUMBER(_xlpm.u),_xlpm.u>0,ISNUMBER(_xlpm.r),_xlpm.r>=0), 1-(_xlpm.r/(_xlpm.q*_xlpm.u)), "" ) ) ) -> 0.02 | J2: =_xlfn.LET( _xlpm.q,RawData!G2, _xlpm.u,RawData!H2, _xlpm.d,RawData!I2, _xlpm.r,RawData!J2, IF(AND(ISNUMBER(_xlpm.r),_xlpm.r>=0),_xlpm.r, IF(AND(ISNUMBER(_xlpm.q),_xlpm.q>0,ISNUMBER(_xlpm.u),_xlpm.u>0,ISNUMBER(_xlpm.d),_xlpm.d>=0,_xlpm.d<1), _xlpm.q*_xlpm.u*(1-_xlpm.d), "" ) ) ) -> 4008.25 | K2: =_xlfn.LET( _xlpm.c,RawData!K2, _xlpm.r,RawData!J2, _xlpm.p,RawData!L2, IF(AND(ISNUMBER(_xlpm.c),_xlpm.c>=0),_xlpm.c, IF(AND(ISNUMBER(_xlpm.r),ISNUMBER(_xlpm.p)), _xlpm.r-_xlpm.p, "" ) ) ) -> 3233.43 | L2: =_xlfn.LET( _xlpm.p,RawData!L2, _xlpm.r,RawData!J2, _xlpm.c,RawData!K2, IF(ISNUMBER(_xlpm.p),_xlpm.p, IF(AND(ISNUMBER(_xlpm.r),ISNUMBER(_xlpm.c)), _xlpm.r-_xlpm.c, "" ) )) -> 774.82
A3: ORD0002 | B3: 45729 | C3: =IF(RawData!C3="","Unknown",PROPER(TRIM(CLEAN(SUBSTITUTE(RawData!C3,CHAR(160)," "))))) -> North | D3: =IF(RawData!D3="","Unknown",PROPER(TRIM(CLEAN(SUBSTITUTE(RawData!D3,CHAR(160)," "))))) -> Lucknow | E3: =IF(RawData!E3="","Unknown",PROPER(TRIM(CLEAN(SUBSTITUTE(RawData!E3,CHAR(160)," "))))) -> Backpack | F3: =IF(RawData!F3="","Unknown",PROPER(TRIM(CLEAN(SUBSTITUTE(RawData!F3,CHAR(160)," "))))) -> Accessories | G3: =_xlfn.LET( _xlpm.q,RawData!G3, _xlpm.u,RawData!H3, _xlpm.d,RawData!I3, _xlpm.r,RawData!J3, IF(AND(ISNUMBER(_xlpm.q),_xlpm.q>0),_xlpm.q, IF(AND(ISNUMBER(_xlpm.r),ISNUMBER(_xlpm.u),_xlpm.u>0,ISNUMBER(_xlpm.d),_xlpm.d>=0,_xlpm.d<1), ROUND(_xlpm.r/(_xlpm.u*(1-_xlpm.d)),0), "" ) ) ) -> 9 | H3: =_xlfn.LET( _xlpm.q,RawData!G3, _xlpm.u,RawData!H3, _xlpm.d,RawData!I3, _xlpm.r,RawData!J3, IF(AND(ISNUMBER(_xlpm.u),_xlpm.u>0),_xlpm.u, IF(AND(ISNUMBER(_xlpm.q),_xlpm.q>0,ISNUMBER(_xlpm.r),ISNUMBER(_xlpm.d),_xlpm.d>=0,_xlpm.d<1), _xlpm.r/(_xlpm.q*(1-_xlpm.d)), "" ) ) ) -> 48.13 | I3: =_xlfn.LET( _xlpm.q,RawData!G3, _xlpm.u,RawData!H3, _xlpm.d,RawData!I3, _xlpm.r,RawData!J3, IF(AND(ISNUMBER(_xlpm.d),_xlpm.d>=0,_xlpm.d<1),_xlpm.d, IF(AND(ISNUMBER(_xlpm.q),_xlpm.q>0,ISNUMBER(_xlpm.u),_xlpm.u>0,ISNUMBER(_xlpm.r),_xlpm.r>=0), 1-(_xlpm.r/(_xlpm.q*_xlpm.u)), "" ) ) ) -> 0 | J3: =_xlfn.LET( _xlpm.q,RawData!G3, _xlpm.u,RawData!H3, _xlpm.d,RawData!I3, _xlpm.r,RawData!J3, IF(AND(ISNUMBER(_xlpm.r),_xlpm.r>=0),_xlpm.r, IF(AND(ISNUMBER(_xlpm.q),_xlpm.q>0,ISNUMBER(_xlpm.u),_xlpm.u>0,ISNUMBER(_xlpm.d),_xlpm.d>=0,_xlpm.d<1), _xlpm.q*_xlpm.u*(1-_xlpm.d), "" ) ) ) -> 433.17 | K3: =_xlfn.LET( _xlpm.c,RawData!K3, _xlpm.r,RawData!J3, _xlpm.p,RawData!L3, IF(AND(ISNUMBER(_xlpm.c),_xlpm.c>=0),_xlpm.c, IF(AND(ISNUMBER(_xlpm.r),ISNUMBER(_xlpm.p)), _xlpm.r-_xlpm.p, "" ) ) ) -> 308.26 | L3: =_xlfn.LET( _xlpm.p,RawData!L3, _xlpm.r,RawData!J3, _xlpm.c,RawData!K3, IF(ISNUMBER(_xlpm.p),_xlpm.p, IF(AND(ISNUMBER(_xlpm.r),ISNUMBER(_xlpm.c)), _xlpm.r-_xlpm.c, "" ) )) -> 124.91
A4: ORD0003 | B4: 45874 | C4: =IF(RawData!C4="","Unknown",PROPER(TRIM(CLEAN(SUBSTITUTE(RawData!C4,CHAR(160)," "))))) -> North | D4: =IF(RawData!D4="","Unknown",PROPER(TRIM(CLEAN(SUBSTITUTE(RawData!D4,CHAR(160)," "))))) -> Delhi | E4: =IF(RawData!E4="","Unknown",PROPER(TRIM(CLEAN(SUBSTITUTE(RawData!E4,CHAR(160)," "))))) -> Laptop | F4: =IF(RawData!F4="","Unknown",PROPER(TRIM(CLEAN(SUBSTITUTE(RawData!F4,CHAR(160)," "))))) -> Electronics | G4: =_xlfn.LET( _xlpm.q,RawData!G4, _xlpm.u,RawData!H4, _xlpm.d,RawData!I4, _xlpm.r,RawData!J4, IF(AND(ISNUMBER(_xlpm.q),_xlpm.q>0),_xlpm.q, IF(AND(ISNUMBER(_xlpm.r),ISNUMBER(_xlpm.u),_xlpm.u>0,ISNUMBER(_xlpm.d),_xlpm.d>=0,_xlpm.d<1), ROUND(_xlpm.r/(_xlpm.u*(1-_xlpm.d)),0), "" ) ) ) -> 2 | H4: =_xlfn.LET( _xlpm.q,RawData!G4, _xlpm.u,RawData!H4, _xlpm.d,RawData!I4, _xlpm.r,RawData!J4, IF(AND(ISNUMBER(_xlpm.u),_xlpm.u>0),_xlpm.u, IF(AND(ISNUMBER(_xlpm.q),_xlpm.q>0,ISNUMBER(_xlpm.r),ISNUMBER(_xlpm.d),_xlpm.d>=0,_xlpm.d<1), _xlpm.r/(_xlpm.q*(1-_xlpm.d)), "" ) ) ) -> 762.28 | I4: =_xlfn.LET( _xlpm.q,RawData!G4, _xlpm.u,RawData!H4, _xlpm.d,RawData!I4, _xlpm.r,RawData!J4, IF(AND(ISNUMBER(_xlpm.d),_xlpm.d>=0,_xlpm.d<1),_xlpm.d, IF(AND(ISNUMBER(_xlpm.q),_xlpm.q>0,ISNUMBER(_xlpm.u),_xlpm.u>0,ISNUMBER(_xlpm.r),_xlpm.r>=0), 1-(_xlpm.r/(_xlpm.q*_xlpm.u)), "" ) ) ) -> 0.02 | J4: =_xlfn.LET( _xlpm.q,RawData!G4, _xlpm.u,RawData!H4, _xlpm.d,RawData!I4, _xlpm.r,RawData!J4, IF(AND(ISNUMBER(_xlpm.r),_xlpm.r>=0),_xlpm.r, IF(AND(ISNUMBER(_xlpm.q),_xlpm.q>0,ISNUMBER(_xlpm.u),_xlpm.u>0,ISNUMBER(_xlpm.d),_xlpm.d>=0,_xlpm.d<1), _xlpm.q*_xlpm.u*(1-_xlpm.d), "" ) ) ) -> 1494.07 | K4: =_xlfn.LET( _xlpm.c,RawData!K4, _xlpm.r,RawData!J4, _xlpm.p,RawData!L4, IF(AND(ISNUMBER(_xlpm.c),_xlpm.c>=0),_xlpm.c, IF(AND(ISNUMBER(_xlpm.r),ISNUMBER(_xlpm.p)), _xlpm.r-_xlpm.p, "" ) ) ) -> 884.67 | L4: =_xlfn.LET( _xlpm.p,RawData!L4, _xlpm.r,RawData!J4, _xlpm.c,RawData!K4, IF(ISNUMBER(_xlpm.p),_xlpm.p, IF(AND(ISNUMBER(_xlpm.r),ISNUMBER(_xlpm.c)), _xlpm.r-_xlpm.c, "" ) )) -> 609.4
A5: ORD0004 | B5: 45916 | C5: =IF(RawData!C5="","Unknown",PROPER(TRIM(CLEAN(SUBSTITUTE(RawData!C5,CHAR(160)," "))))) -> North | D5: =IF(RawData!D5="","Unknown",PROPER(TRIM(CLEAN(SUBSTITUTE(RawData!D5,CHAR(160)," "))))) -> Lucknow | E5: =IF(RawData!E5="","Unknown",PROPER(TRIM(CLEAN(SUBSTITUTE(RawData!E5,CHAR(160)," "))))) -> Notebook | F5: =IF(RawData!F5="","Unknown",PROPER(TRIM(CLEAN(SUBSTITUTE(RawData!F5,CHAR(160)," "))))) -> Office Supplies | G5: =_xlfn.LET( _xlpm.q,RawData!G5, _xlpm.u,RawData!H5, _xlpm.d,RawData!I5, _xlpm.r,RawData!J5, IF(AND(ISNUMBER(_xlpm.q),_xlpm.q>0),_xlpm.q, IF(AND(ISNUMBER(_xlpm.r),ISNUMBER(_xlpm.u),_xlpm.u>0,ISNUMBER(_xlpm.d),_xlpm.d>=0,_xlpm.d<1), ROUND(_xlpm.r/(_xlpm.u*(1-_xlpm.d)),0), "" ) ) ) -> 4 | H5: =_xlfn.LET( _xlpm.q,RawData!G5, _xlpm.u,RawData!H5, _xlpm.d,RawData!I5, _xlpm.r,RawData!J5, IF(AND(ISNUMBER(_xlpm.u),_xlpm.u>0),_xlpm.u, IF(AND(ISNUMBER(_xlpm.q),_xlpm.q>0,ISNUMBER(_xlpm.r),ISNUMBER(_xlpm.d),_xlpm.d>=0,_xlpm.d<1), _xlpm.r/(_xlpm.q*(1-_xlpm.d)), "" ) ) ) -> 6.94 | I5: =_xlfn.LET( _xlpm.q,RawData!G5, _xlpm.u,RawData!H5, _xlpm.d,RawData!I5, _xlpm.r,RawData!J5, IF(AND(ISNUMBER(_xlpm.d),_xlpm.d>=0,_xlpm.d<1),_xlpm.d, IF(AND(ISNUMBER(_xlpm.q),_xlpm.q>0,ISNUMBER(_xlpm.u),_xlpm.u>0,ISNUMBER(_xlpm.r),_xlpm.r>=0), 1-(_xlpm.r/(_xlpm.q*_xlpm.u)), "" ) ) ) -> 0.2 | J5: =_xlfn.LET( _xlpm.q,RawData!G5, _xlpm.u,RawData!H5, _xlpm.d,RawData!I5, _xlpm.r,RawData!J5, IF(AND(ISNUMBER(_xlpm.r),_xlpm.r>=0),_xlpm.r, IF(AND(ISNUMBER(_xlpm.q),_xlpm.q>0,ISNUMBER(_xlpm.u),_xlpm.u>0,ISNUMBER(_xlpm.d),_xlpm.d>=0,_xlpm.d<1), _xlpm.q*_xlpm.u*(1-_xlpm.d), "" ) ) ) -> 22.21 | K5: =_xlfn.LET( _xlpm.c,RawData!K5, _xlpm.r,RawData!J5, _xlpm.p,RawData!L5, IF(AND(ISNUMBER(_xlpm.c),_xlpm.c>=0),_xlpm.c, IF(AND(ISNUMBER(_xlpm.r),ISNUMBER(_xlpm.p)), _xlpm.r-_xlpm.p, "" ) ) ) -> 17.41 | L5: =_xlfn.LET( _xlpm.p,RawData!L5, _xlpm.r,RawData!J5, _xlpm.c,RawData!K5, IF(ISNUMBER(_xlpm.p),_xlpm.p, IF(AND(ISNUMBER(_xlpm.r),ISNUMBER(_xlpm.c)), _xlpm.r-_xlpm.c, "" ) )) -> 4.8
A6: ORD0005 | B6: 46017 | C6: =IF(RawData!C6="","Unknown",PROPER(TRIM(CLEAN(SUBSTITUTE(RawData!C6,CHAR(160)," "))))) -> West | D6: =IF(RawData!D6="","Unknown",PROPER(TRIM(CLEAN(SUBSTITUTE(RawData!D6,CHAR(160)," "))))) -> Pune | E6: =IF(RawData!E6="","Unknown",PROPER(TRIM(CLEAN(SUBSTITUTE(RawData!E6,CHAR(160)," "))))) -> Monitor | F6: =IF(RawData!F6="","Unknown",PROPER(TRIM(CLEAN(SUBSTITUTE(RawData!F6,CHAR(160)," "))))) -> Electronics | G6: =_xlfn.LET( _xlpm.q,RawData!G6, _xlpm.u,RawData!H6, _xlpm.d,RawData!I6, _xlpm.r,RawData!J6, IF(AND(ISNUMBER(_xlpm.q),_xlpm.q>0),_xlpm.q, IF(AND(ISNUMBER(_xlpm.r),ISNUMBER(_xlpm.u),_xlpm.u>0,ISNUMBER(_xlpm.d),_xlpm.d>=0,_xlpm.d<1), ROUND(_xlpm.r/(_xlpm.u*(1-_xlpm.d)),0), "" ) ) ) -> 8 | H6: =_xlfn.LET( _xlpm.q,RawData!G6, _xlpm.u,RawData!H6, _xlpm.d,RawData!I6, _xlpm.r,RawData!J6, IF(AND(ISNUMBER(_xlpm.u),_xlpm.u>0),_xlpm.u, IF(AND(ISNUMBER(_xlpm.q),_xlpm.q>0,ISNUMBER(_xlpm.r),ISNUMBER(_xlpm.d),_xlpm.d>=0,_xlpm.d<1), _xlpm.r/(_xlpm.q*(1-_xlpm.d)), "" ) ) ) -> 226.67 | I6: =_xlfn.LET( _xlpm.q,RawData!G6, _xlpm.u,RawData!H6, _xlpm.d,RawData!I6, _xlpm.r,RawData!J6, IF(AND(ISNUMBER(_xlpm.d),_xlpm.d>=0,_xlpm.d<1),_xlpm.d, IF(AND(ISNUMBER(_xlpm.q),_xlpm.q>0,ISNUMBER(_xlpm.u),_xlpm.u>0,ISNUMBER(_xlpm.r),_xlpm.r>=0), 1-(_xlpm.r/(_xlpm.q*_xlpm.u)), "" ) ) ) -> 0.15 | J6: =_xlfn.LET( _xlpm.q,RawData!G6, _xlpm.u,RawData!H6, _xlpm.d,RawData!I6, _xlpm.r,RawData!J6, IF(AND(ISNUMBER(_xlpm.r),_xlpm.r>=0),_xlpm.r, IF(AND(ISNUMBER(_xlpm.q),_xlpm.q>0,ISNUMBER(_xlpm.u),_xlpm.u>0,ISNUMBER(_xlpm.d),_xlpm.d>=0,_xlpm.d<1), _xlpm.q*_xlpm.u*(1-_xlpm.d), "" ) ) ) -> 1541.36 | K6: =_xlfn.LET( _xlpm.c,RawData!K6, _xlpm.r,RawData!J6, _xlpm.p,RawData!L6, IF(AND(ISNUMBER(_xlpm.c),_xlpm.c>=0),_xlpm.c, IF(AND(ISNUMBER(_xlpm.r),ISNUMBER(_xlpm.p)), _xlpm.r-_xlpm.p, "" ) ) ) -> 1142.42 | L6: =_xlfn.LET( _xlpm.p,RawData!L6, _xlpm.r,RawData!J6, _xlpm.c,RawData!K6, IF(ISNUMBER(_xlpm.p),_xlpm.p, IF(AND(ISNUMBER(_xlpm.r),ISNUMBER(_xlpm.c)), _xlpm.r-_xlpm.c, "" ) )) -> 398.94
A7: ORD0006 | B7: 45661 | C7: =IF(RawData!C7="","Unknown",PROPER(TRIM(CLEAN(SUBSTITUTE(RawData!C7,CHAR(160)," "))))) -> South | D7: =IF(RawData!D7="","Unknown",PROPER(TRIM(CLEAN(SUBSTITUTE(RawData!D7,CHAR(160)," "))))) -> Chennai | E7: =IF(RawData!E7="","Unknown",PROPER(TRIM(CLEAN(SUBSTITUTE(RawData!E7,CHAR(160)," "))))) -> Keyboard | F7: =IF(RawData!F7="","Unknown",PROPER(TRIM(CLEAN(SUBSTITUTE(RawData!F7,CHAR(160)," "))))) -> Accessories | G7: =_xlfn.LET( _xlpm.q,RawData!G7, _xlpm.u,RawData!H7, _xlpm.d,RawData!I7, _xlpm.r,RawData!J7, IF(AND(ISNUMBER(_xlpm.q),_xlpm.q>0),_xlpm.q, IF(AND(ISNUMBER(_xlpm.r),ISNUMBER(_xlpm.u),_xlpm.u>0,ISNUMBER(_xlpm.d),_xlpm.d>=0,_xlpm.d<1), ROUND(_xlpm.r/(_xlpm.u*(1-_xlpm.d)),0), "" ) ) ) -> 7 | H7: =_xlfn.LET( _xlpm.q,RawData!G7, _xlpm.u,RawData!H7, _xlpm.d,RawData!I7, _xlpm.r,RawData!J7, IF(AND(ISNUMBER(_xlpm.u),_xlpm.u>0),_xlpm.u, IF(AND(ISNUMBER(_xlpm.q),_xlpm.q>0,ISNUMBER(_xlpm.r),ISNUMBER(_xlpm.d),_xlpm.d>=0,_xlpm.d<1), _xlpm.r/(_xlpm.q*(1-_xlpm.d)), "" ) ) ) -> 29.97 | I7: =_xlfn.LET( _xlpm.q,RawData!G7, _xlpm.u,RawData!H7, _xlpm.d,RawData!I7, _xlpm.r,RawData!J7, IF(AND(ISNUMBER(_xlpm.d),_xlpm.d>=0,_xlpm.d<1),_xlpm.d, IF(AND(ISNUMBER(_xlpm.q),_xlpm.q>0,ISNUMBER(_xlpm.u),_xlpm.u>0,ISNUMBER(_xlpm.r),_xlpm.r>=0), 1-(_xlpm.r/(_xlpm.q*_xlpm.u)), "" ) ) ) -> 0.05 | J7: =_xlfn.LET( _xlpm.q,RawData!G7, _xlpm.u,RawData!H7, _xlpm.d,RawData!I7, _xlpm.r,RawData!J7, IF(AND(ISNUMBER(_xlpm.r),_xlpm.r>=0),_xlpm.r, IF(AND(ISNUMBER(_xlpm.q),_xlpm.q>0,ISNUMBER(_xlpm.u),_xlpm.u>0,ISNUMBER(_xlpm.d),_xlpm.d>=0,_xlpm.d<1), _xlpm.q*_xlpm.u*(1-_xlpm.d), "" ) ) ) -> 199.3 | K7: =_xlfn.LET( _xlpm.c,RawData!K7, _xlpm.r,RawData!J7, _xlpm.p,RawData!L7, IF(AND(ISNUMBER(_xlpm.c),_xlpm.c>=0),_xlpm.c, IF(AND(ISNUMBER(_xlpm.r),ISNUMBER(_xlpm.p)), _xlpm.r-_xlpm.p, "" ) ) ) -> 161.81 | L7: =_xlfn.LET( _xlpm.p,RawData!L7, _xlpm.r,RawData!J7, _xlpm.c,RawData!K7, IF(ISNUMBER(_xlpm.p),_xlpm.p, IF(AND(ISNUMBER(_xlpm.r),ISNUMBER(_xlpm.c)), _xlpm.r-_xlpm.c, "" ) )) -> 37.49
A8: ORD0007 | B8: 45737 | C8: =IF(RawData!C8="","Unknown",PROPER(TRIM(CLEAN(SUBSTITUTE(RawData!C8,CHAR(160)," "))))) -> South | D8: =IF(RawData!D8="","Unknown",PROPER(TRIM(CLEAN(SUBSTITUTE(RawData!D8,CHAR(160)," "))))) -> Chennai | E8: =IF(RawData!E8="","Unknown",PROPER(TRIM(CLEAN(SUBSTITUTE(RawData!E8,CHAR(160)," "))))) -> Desk | F8: =IF(RawData!F8="","Unknown",PROPER(TRIM(CLEAN(SUBSTITUTE(RawData!F8,CHAR(160)," "))))) -> Furniture | G8: =_xlfn.LET( _xlpm.q,RawData!G8, _xlpm.u,RawData!H8, _xlpm.d,RawData!I8, _xlpm.r,RawData!J8, IF(AND(ISNUMBER(_xlpm.q),_xlpm.q>0),_xlpm.q, IF(AND(ISNUMBER(_xlpm.r),ISNUMBER(_xlpm.u),_xlpm.u>0,ISNUMBER(_xlpm.d),_xlpm.d>=0,_xlpm.d<1), ROUND(_xlpm.r/(_xlpm.u*(1-_xlpm.d)),0), "" ) ) ) -> 2 | H8: =_xlfn.LET( _xlpm.q,RawData!G8, _xlpm.u,RawData!H8, _xlpm.d,RawData!I8, _xlpm.r,RawData!J8, IF(AND(ISNUMBER(_xlpm.u),_xlpm.u>0),_xlpm.u, IF(AND(ISNUMBER(_xlpm.q),_xlpm.q>0,ISNUMBER(_xlpm.r),ISNUMBER(_xlpm.d),_xlpm.d>=0,_xlpm.d<1), _xlpm.r/(_xlpm.q*(1-_xlpm.d)), "" ) ) ) -> 274.93 | I8: =_xlfn.LET( _xlpm.q,RawData!G8, _xlpm.u,RawData!H8, _xlpm.d,RawData!I8, _xlpm.r,RawData!J8, IF(AND(ISNUMBER(_xlpm.d),_xlpm.d>=0,_xlpm.d<1),_xlpm.d, IF(AND(ISNUMBER(_xlpm.q),_xlpm.q>0,ISNUMBER(_xlpm.u),_xlpm.u>0,ISNUMBER(_xlpm.r),_xlpm.r>=0), 1-(_xlpm.r/(_xlpm.q*_xlpm.u)), "" ) ) ) -> 0 | J8: =_xlfn.LET( _xlpm.q,RawData!G8, _xlpm.u,RawData!H8, _xlpm.d,RawData!I8, _xlpm.r,RawData!J8, IF(AND(ISNUMBER(_xlpm.r),_xlpm.r>=0),_xlpm.r, IF(AND(ISNUMBER(_xlpm.q),_xlpm.q>0,ISNUMBER(_xlpm.u),_xlpm.u>0,ISNUMBER(_xlpm.d),_xlpm.d>=0,_xlpm.d<1), _xlpm.q*_xlpm.u*(1-_xlpm.d), "" ) ) ) -> 549.86 | K8: =_xlfn.LET( _xlpm.c,RawData!K8, _xlpm.r,RawData!J8, _xlpm.p,RawData!L8, IF(AND(ISNUMBER(_xlpm.c),_xlpm.c>=0),_xlpm.c, IF(AND(ISNUMBER(_xlpm.r),ISNUMBER(_xlpm.p)), _xlpm.r-_xlpm.p, "" ) ) ) -> 333.95 | L8: =_xlfn.LET( _xlpm.p,RawData!L8, _xlpm.r,RawData!J8, _xlpm.c,RawData!K8, IF(ISNUMBER(_xlpm.p),_xlpm.p, IF(AND(ISNUMBER(_xlpm.r),ISNUMBER(_xlpm.c)), _xlpm.r-_xlpm.c, "" ) )) -> 215.91
A9: ORD0008 | B9: 45707 | C9: =IF(RawData!C9="","Unknown",PROPER(TRIM(CLEAN(SUBSTITUTE(RawData!C9,CHAR(160)," "))))) -> East | D9: =IF(RawData!D9="","Unknown",PROPER(TRIM(CLEAN(SUBSTITUTE(RawData!D9,CHAR(160)," "))))) -> Hyderabad | E9: =IF(RawData!E9="","Unknown",PROPER(TRIM(CLEAN(SUBSTITUTE(RawData!E9,CHAR(160)," "))))) -> Desk | F9: =IF(RawData!F9="","Unknown",PROPER(TRIM(CLEAN(SUBSTITUTE(RawData!F9,CHAR(160)," "))))) -> Furniture | G9: =_xlfn.LET( _xlpm.q,RawData!G9, _xlpm.u,RawData!H9, _xlpm.d,RawData!I9, _xlpm.r,RawData!J9, IF(AND(ISNUMBER(_xlpm.q),_xlpm.q>0),_xlpm.q, IF(AND(ISNUMBER(_xlpm.r),ISNUMBER(_xlpm.u),_xlpm.u>0,ISNUMBER(_xlpm.d),_xlpm.d>=0,_xlpm.d<1), ROUND(_xlpm.r/(_xlpm.u*(1-_xlpm.d)),0), "" ) ) ) -> 10 | H9: =_xlfn.LET( _xlpm.q,RawData!G9, _xlpm.u,RawData!H9, _xlpm.d,RawData!I9, _xlpm.r,RawData!J9, IF(AND(ISNUMBER(_xlpm.u),_xlpm.u>0),_xlpm.u, IF(AND(ISNUMBER(_xlpm.q),_xlpm.q>0,ISNUMBER(_xlpm.r),ISNUMBER(_xlpm.d),_xlpm.d>=0,_xlpm.d<1), _xlpm.r/(_xlpm.q*(1-_xlpm.d)), "" ) ) ) -> 226.14 | I9: =_xlfn.LET( _xlpm.q,RawData!G9, _xlpm.u,RawData!H9, _xlpm.d,RawData!I9, _xlpm.r,RawData!J9, IF(AND(ISNUMBER(_xlpm.d),_xlpm.d>=0,_xlpm.d<1),_xlpm.d, IF(AND(ISNUMBER(_xlpm.q),_xlpm.q>0,ISNUMBER(_xlpm.u),_xlpm.u>0,ISNUMBER(_xlpm.r),_xlpm.r>=0), 1-(_xlpm.r/(_xlpm.q*_xlpm.u)), "" ) ) ) -> 0.05 | J9: =_xlfn.LET( _xlpm.q,RawData!G9, _xlpm.u,RawData!H9, _xlpm.d,RawData!I9, _xlpm.r,RawData!J9, IF(AND(ISNUMBER(_xlpm.r),_xlpm.r>=0),_xlpm.r, IF(AND(ISNUMBER(_xlpm.q),_xlpm.q>0,ISNUMBER(_xlpm.u),_xlpm.u>0,ISNUMBER(_xlpm.d),_xlpm.d>=0,_xlpm.d<1), _xlpm.q*_xlpm.u*(1-_xlpm.d), "" ) ) ) -> 2148.33 | K9: =_xlfn.LET( _xlpm.c,RawData!K9, _xlpm.r,RawData!J9, _xlpm.p,RawData!L9, IF(AND(ISNUMBER(_xlpm.c),_xlpm.c>=0),_xlpm.c, IF(AND(ISNUMBER(_xlpm.r),ISNUMBER(_xlpm.p)), _xlpm.r-_xlpm.p, "" ) ) ) -> 1287.97 | L9: =_xlfn.LET( _xlpm.p,RawData!L9, _xlpm.r,RawData!J9, _xlpm.c,RawData!K9, IF(ISNUMBER(_xlpm.p),_xlpm.p, IF(AND(ISNUMBER(_xlpm.r),ISNUMBER(_xlpm.c)), _xlpm.r-_xlpm.c, "" ) )) -> 860.36
A10: ORD0009 | B10: 45893 | C10: =IF(RawData!C10="","Unknown",PROPER(TRIM(CLEAN(SUBSTITUTE(RawData!C10,CHAR(160)," "))))) -> North | D10: =IF(RawData!D10="","Unknown",PROPER(TRIM(CLEAN(SUBSTITUTE(RawData!D10,CHAR(160)," "))))) -> Jaipur | E10: =IF(RawData!E10="","Unknown",PROPER(TRIM(CLEAN(SUBSTITUTE(RawData!E10,CHAR(160)," "))))) -> Bookshelf | F10: =IF(RawData!F10="","Unknown",PROPER(TRIM(CLEAN(SUBSTITUTE(RawData!F10,CHAR(160)," "))))) -> Furniture | G10: =_xlfn.LET( _xlpm.q,RawData!G10, _xlpm.u,RawData!H10, _xlpm.d,RawData!I10, _xlpm.r,RawData!J10, IF(AND(ISNUMBER(_xlpm.q),_xlpm.q>0),_xlpm.q, IF(AND(ISNUMBER(_xlpm.r),ISNUMBER(_xlpm.u),_xlpm.u>0,ISNUMBER(_xlpm.d),_xlpm.d>=0,_xlpm.d<1), ROUND(_xlpm.r/(_xlpm.u*(1-_xlpm.d)),0), "" ) ) ) -> 2 | H10: =_xlfn.LET( _xlpm.q,RawData!G10, _xlpm.u,RawData!H10, _xlpm.d,RawData!I10, _xlpm.r,RawData!J10, IF(AND(ISNUMBER(_xlpm.u),_xlpm.u>0),_xlpm.u, IF(AND(ISNUMBER(_xlpm.q),_xlpm.q>0,ISNUMBER(_xlpm.r),ISNUMBER(_xlpm.d),_xlpm.d>=0,_xlpm.d<1), _xlpm.r/(_xlpm.q*(1-_xlpm.d)), "" ) ) ) -> 131.78 | I10: =_xlfn.LET( _xlpm.q,RawData!G10, _xlpm.u,RawData!H10, _xlpm.d,RawData!I10, _xlpm.r,RawData!J10, IF(AND(ISNUMBER(_xlpm.d),_xlpm.d>=0,_xlpm.d<1),_xlpm.d, IF(AND(ISNUMBER(_xlpm.q),_xlpm.q>0,ISNUMBER(_xlpm.u),_xlpm.u>0,ISNUMBER(_xlpm.r),_xlpm.r>=0), 1-(_xlpm.r/(_xlpm.q*_xlpm.u)), "" ) ) ) -> 0.15 | J10: =_xlfn.LET( _xlpm.q,RawData!G10, _xlpm.u,RawData!H10, _xlpm.d,RawData!I10, _xlpm.r,RawData!J10, IF(AND(ISNUMBER(_xlpm.r),_xlpm.r>=0),_xlpm.r, IF(AND(ISNUMBER(_xlpm.q),_xlpm.q>0,ISNUMBER(_xlpm.u),_xlpm.u>0,ISNUMBER(_xlpm.d),_xlpm.d>=0,_xlpm.d<1), _xlpm.q*_xlpm.u*(1-_xlpm.d), "" ) ) ) -> 224.03 | K10: =_xlfn.LET( _xlpm.c,RawData!K10, _xlpm.r,RawData!J10, _xlpm.p,RawData!L10, IF(AND(ISNUMBER(_xlpm.c),_xlpm.c>=0),_xlpm.c, IF(AND(ISNUMBER(_xlpm.r),ISNUMBER(_xlpm.p)), _xlpm.r-_xlpm.p, "" ) ) ) -> 154.96 | L10: =_xlfn.LET( _xlpm.p,RawData!L10, _xlpm.r,RawData!J10, _xlpm.c,RawData!K10, IF(ISNUMBER(_xlpm.p),_xlpm.p, IF(AND(ISNUMBER(_xlpm.r),ISNUMBER(_xlpm.c)), _xlpm.r-_xlpm.c, "" ) )) -> 69.07
A11: ORD0010 | B11: 45979 | C11: =IF(RawData!C11="","Unknown",PROPER(TRIM(CLEAN(SUBSTITUTE(RawData!C11,CHAR(160)," "))))) -> East | D11: =IF(RawData!D11="","Unknown",PROPER(TRIM(CLEAN(SUBSTITUTE(RawData!D11,CHAR(160)," "))))) -> Kolkata | E11: =IF(RawData!E11="","Unknown",PROPER(TRIM(CLEAN(SUBSTITUTE(RawData!E11,CHAR(160)," "))))) -> Pen Set | F11: =IF(RawData!F11="","Unknown",PROPER(TRIM(CLEAN(SUBSTITUTE(RawData!F11,CHAR(160)," "))))) -> Office Supplies | G11: =_xlfn.LET( _xlpm.q,RawData!G11, _xlpm.u,RawData!H11, _xlpm.d,RawData!I11, _xlpm.r,RawData!J11, IF(AND(ISNUMBER(_xlpm.q),_xlpm.q>0),_xlpm.q, IF(AND(ISNUMBER(_xlpm.r),ISNUMBER(_xlpm.u),_xlpm.u>0,ISNUMBER(_xlpm.d),_xlpm.d>=0,_xlpm.d<1), ROUND(_xlpm.r/(_xlpm.u*(1-_xlpm.d)),0), "" ) ) ) -> 4 | H11: =_xlfn.LET( _xlpm.q,RawData!G11, _xlpm.u,RawData!H11, _xlpm.d,RawData!I11, _xlpm.r,RawData!J11, IF(AND(ISNUMBER(_xlpm.u),_xlpm.u>0),_xlpm.u, IF(AND(ISNUMBER(_xlpm.q),_xlpm.q>0,ISNUMBER(_xlpm.r),ISNUMBER(_xlpm.d),_xlpm.d>=0,_xlpm.d<1), _xlpm.r/(_xlpm.q*(1-_xlpm.d)), "" ) ) ) -> 11.76 | I11: =_xlfn.LET( _xlpm.q,RawData!G11, _xlpm.u,RawData!H11, _xlpm.d,RawData!I11, _xlpm.r,RawData!J11, IF(AND(ISNUMBER(_xlpm.d),_xlpm.d>=0,_xlpm.d<1),_xlpm.d, IF(AND(ISNUMBER(_xlpm.q),_xlpm.q>0,ISNUMBER(_xlpm.u),_xlpm.u>0,ISNUMBER(_xlpm.r),_xlpm.r>=0), 1-(_xlpm.r/(_xlpm.q*_xlpm.u)), "" ) ) ) -> 0.2 | J11: =_xlfn.LET( _xlpm.q,RawData!G11, _xlpm.u,RawData!H11, _xlpm.d,RawData!I11, _xlpm.r,RawData!J11, IF(AND(ISNUMBER(_xlpm.r),_xlpm.r>=0),_xlpm.r, IF(AND(ISNUMBER(_xlpm.q),_xlpm.q>0,ISNUMBER(_xlpm.u),_xlpm.u>0,ISNUMBER(_xlpm.d),_xlpm.d>=0,_xlpm.d<1), _xlpm.q*_xlpm.u*(1-_xlpm.d), "" ) ) ) -> 37.63 | K11: =_xlfn.LET( _xlpm.c,RawData!K11, _xlpm.r,RawData!J11, _xlpm.p,RawData!L11, IF(AND(ISNUMBER(_xlpm.c),_xlpm.c>=0),_xlpm.c, IF(AND(ISNUMBER(_xlpm.r),ISNUMBER(_xlpm.p)), _xlpm.r-_xlpm.p, "" ) ) ) -> 23.66 | L11: =_xlfn.LET( _xlpm.p,RawData!L11, _xlpm.r,RawData!J11, _xlpm.c,RawData!K11, IF(ISNUMBER(_xlpm.p),_xlpm.p, IF(AND(ISNUMBER(_xlpm.r),ISNUMBER(_xlpm.c)), _xlpm.r-_xlpm.c, "" ) )) -> 13.97
A12: ORD0011 | B12: 45681 | C12: =IF(RawData!C12="","Unknown",PROPER(TRIM(CLEAN(SUBSTITUTE(RawData!C12,CHAR(160)," "))))) -> South | D12: =IF(RawData!D12="","Unknown",PROPER(TRIM(CLEAN(SUBSTITUTE(RawData!D12,CHAR(160)," "))))) -> Hyderabad | E12: =IF(RawData!E12="","Unknown",PROPER(TRIM(CLEAN(SUBSTITUTE(RawData!E12,CHAR(160)," "))))) -> Office Chair | F12: =IF(RawData!F12="","Unknown",PROPER(TRIM(CLEAN(SUBSTITUTE(RawData!F12,CHAR(160)," "))))) -> Furniture | G12: =_xlfn.LET( _xlpm.q,RawData!G12, _xlpm.u,RawData!H12, _xlpm.d,RawData!I12, _xlpm.r,RawData!J12, IF(AND(ISNUMBER(_xlpm.q),_xlpm.q>0),_xlpm.q, IF(AND(ISNUMBER(_xlpm.r),ISNUMBER(_xlpm.u),_xlpm.u>0,ISNUMBER(_xlpm.d),_xlpm.d>=0,_xlpm.d<1), ROUND(_xlpm.r/(_xlpm.u*(1-_xlpm.d)),0), "" ) ) ) -> 2 | H12: =_xlfn.LET( _xlpm.q,RawData!G12, _xlpm.u,RawData!H12, _xlpm.d,RawData!I12, _xlpm.r,RawData!J12, IF(AND(ISNUMBER(_xlpm.u),_xlpm.u>0),_xlpm.u, IF(AND(ISNUMBER(_xlpm.q),_xlpm.q>0,ISNUMBER(_xlpm.r),ISNUMBER(_xlpm.d),_xlpm.d>=0,_xlpm.d<1), _xlpm.r/(_xlpm.q*(1-_xlpm.d)), "" ) ) ) -> 186.04 | I12: =_xlfn.LET( _xlpm.q,RawData!G12, _xlpm.u,RawData!H12, _xlpm.d,RawData!I12, _xlpm.r,RawData!J12, IF(AND(ISNUMBER(_xlpm.d),_xlpm.d>=0,_xlpm.d<1),_xlpm.d, IF(AND(ISNUMBER(_xlpm.q),_xlpm.q>0,ISNUMBER(_xlpm.u),_xlpm.u>0,ISNUMBER(_xlpm.r),_xlpm.r>=0), 1-(_xlpm.r/(_xlpm.q*_xlpm.u)), "" ) ) ) -> 0.02 | J12: =_xlfn.LET( _xlpm.q,RawData!G12, _xlpm.u,RawData!H12, _xlpm.d,RawData!I12, _xlpm.r,RawData!J12, IF(AND(ISNUMBER(_xlpm.r),_xlpm.r>=0),_xlpm.r, IF(AND(ISNUMBER(_xlpm.q),_xlpm.q>0,ISNUMBER(_xlpm.u),_xlpm.u>0,ISNUMBER(_xlpm.d),_xlpm.d>=0,_xlpm.d<1), _xlpm.q*_xlpm.u*(1-_xlpm.d), "" ) ) ) -> 364.64 | K12: =_xlfn.LET( _xlpm.c,RawData!K12, _xlpm.r,RawData!J12, _xlpm.p,RawData!L12, IF(AND(ISNUMBER(_xlpm.c),_xlpm.c>=0),_xlpm.c, IF(AND(ISNUMBER(_xlpm.r),ISNUMBER(_xlpm.p)), _xlpm.r-_xlpm.p, "" ) ) ) -> 214.29 | L12: =_xlfn.LET( _xlpm.p,RawData!L12, _xlpm.r,RawData!J12, _xlpm.c,RawData!K12, IF(ISNUMBER(_xlpm.p),_xlpm.p, IF(AND(ISNUMBER(_xlpm.r),ISNUMBER(_xlpm.c)), _xlpm.r-_xlpm.c, "" ) )) -> 150.35
A13: ORD0012 | B13: 45852 | C13: =IF(RawData!C13="","Unknown",PROPER(TRIM(CLEAN(SUBSTITUTE(RawData!C13,CHAR(160)," "))))) -> East | D13: =IF(RawData!D13="","Unknown",PROPER(TRIM(CLEAN(SUBSTITUTE(RawData!D13,CHAR(160)," "))))) -> Bhubaneswar | E13: =IF(RawData!E13="","Unknown",PROPER(TRIM(CLEAN(SUBSTITUTE(RawData!E13,CHAR(160)," "))))) -> Printer | F13: =IF(RawData!F13="","Unknown",PROPER(TRIM(CLEAN(SUBSTITUTE(RawData!F13,CHAR(160)," "))))) -> Office Supplies | G13: =_xlfn.LET( _xlpm.q,RawData!G13, _xlpm.u,RawData!H13, _xlpm.d,RawData!I13, _xlpm.r,RawData!J13, IF(AND(ISNUMBER(_xlpm.q),_xlpm.q>0),_xlpm.q, IF(AND(ISNUMBER(_xlpm.r),ISNUMBER(_xlpm.u),_xlpm.u>0,ISNUMBER(_xlpm.d),_xlpm.d>=0,_xlpm.d<1), ROUND(_xlpm.r/(_xlpm.u*(1-_xlpm.d)),0), "" ) ) ) -> 6 | H13: =_xlfn.LET( _xlpm.q,RawData!G13, _xlpm.u,RawData!H13, _xlpm.d,RawData!I13, _xlpm.r,RawData!J13, IF(AND(ISNUMBER(_xlpm.u),_xlpm.u>0),_xlpm.u, IF(AND(ISNUMBER(_xlpm.q),_xlpm.q>0,ISNUMBER(_xlpm.r),ISNUMBER(_xlpm.d),_xlpm.d>=0,_xlpm.d<1), _xlpm.r/(_xlpm.q*(1-_xlpm.d)), "" ) ) ) -> 150.02 | I13: =_xlfn.LET( _xlpm.q,RawData!G13, _xlpm.u,RawData!H13, _xlpm.d,RawData!I13, _xlpm.r,RawData!J13, IF(AND(ISNUMBER(_xlpm.d),_xlpm.d>=0,_xlpm.d<1),_xlpm.d, IF(AND(ISNUMBER(_xlpm.q),_xlpm.q>0,ISNUMBER(_xlpm.u),_xlpm.u>0,ISNUMBER(_xlpm.r),_xlpm.r>=0), 1-(_xlpm.r/(_xlpm.q*_xlpm.u)), "" ) ) ) -> 0.02 | J13: =_xlfn.LET( _xlpm.q,RawData!G13, _xlpm.u,RawData!H13, _xlpm.d,RawData!I13, _xlpm.r,RawData!J13, IF(AND(ISNUMBER(_xlpm.r),_xlpm.r>=0),_xlpm.r, IF(AND(ISNUMBER(_xlpm.q),_xlpm.q>0,ISNUMBER(_xlpm.u),_xlpm.u>0,ISNUMBER(_xlpm.d),_xlpm.d>=0,_xlpm.d<1), _xlpm.q*_xlpm.u*(1-_xlpm.d), "" ) ) ) -> 882.12 | K13: =_xlfn.LET( _xlpm.c,RawData!K13, _xlpm.r,RawData!J13, _xlpm.p,RawData!L13, IF(AND(ISNUMBER(_xlpm.c),_xlpm.c>=0),_xlpm.c, IF(AND(ISNUMBER(_xlpm.r),ISNUMBER(_xlpm.p)), _xlpm.r-_xlpm.p, "" ) ) ) -> 572.42 | L13: =_xlfn.LET( _xlpm.p,RawData!L13, _xlpm.r,RawData!J13, _xlpm.c,RawData!K13, IF(ISNUMBER(_xlpm.p),_xlpm.p, IF(AND(ISNUMBER(_xlpm.r),ISNUMBER(_xlpm.c)), _xlpm.r-_xlpm.c, "" ) )) -> 309.7
... A535: ORD0534 | B535: 46018 | C535: =IF(RawData!C535="","Unknown",PROPER(TRIM(CLEAN(SUBSTITUTE(RawData!C535,CHAR(160)," "))))) -> South | D535: =IF(RawData!D535="","Unknown",PROPER(TRIM(CLEAN(SUBSTITUTE(RawData!D535,CHAR(160)," "))))) -> Hyderabad | E535: =IF(RawData!E535="","Unknown",PROPER(TRIM(CLEAN(SUBSTITUTE(RawData!E535,CHAR(160)," "))))) -> Monitor | F535: =IF(RawData!F535="","Unknown",PROPER(TRIM(CLEAN(SUBSTITUTE(RawData!F535,CHAR(160)," "))))) -> Electronics | G535: =_xlfn.LET( _xlpm.q,RawData!G535, _xlpm.u,RawData!H535, _xlpm.d,RawData!I535, _xlpm.r,RawData!J535, IF(AND(ISNUMBER(_xlpm.q),_xlpm.q>0),_xlpm.q, IF(AND(ISNUMBER(_xlpm.r),ISNUMBER(_xlpm.u),_xlpm.u>0,ISNUMBER(_xlpm.d),_xlpm.d>=0,_xlpm.d<1), ROUND(_xlpm.r/(_xlpm.u*(1-_xlpm.d)),0), "" ) ) ) -> 5 | H535: =_xlfn.LET( _xlpm.q,RawData!G535, _xlpm.u,RawData!H535, _xlpm.d,RawData!I535, _xlpm.r,RawData!J535, IF(AND(ISNUMBER(_xlpm.u),_xlpm.u>0),_xlpm.u, IF(AND(ISNUMBER(_xlpm.q),_xlpm.q>0,ISNUMBER(_xlpm.r),ISNUMBER(_xlpm.d),_xlpm.d>=0,_xlpm.d<1), _xlpm.r/(_xlpm.q*(1-_xlpm.d)), "" ) ) ) -> 202.76 | I535: =_xlfn.LET( _xlpm.q,RawData!G535, _xlpm.u,RawData!H535, _xlpm.d,RawData!I535, _xlpm.r,RawData!J535, IF(AND(ISNUMBER(_xlpm.d),_xlpm.d>=0,_xlpm.d<1),_xlpm.d, IF(AND(ISNUMBER(_xlpm.q),_xlpm.q>0,ISNUMBER(_xlpm.u),_xlpm.u>0,ISNUMBER(_xlpm.r),_xlpm.r>=0), 1-(_xlpm.r/(_xlpm.q*_xlpm.u)), "" ) ) ) -> 0.2 | J535: =_xlfn.LET( _xlpm.q,RawData!G535, _xlpm.u,RawData!H535, _xlpm.d,RawData!I535, _xlpm.r,RawData!J535, IF(AND(ISNUMBER(_xlpm.r),_xlpm.r>=0),_xlpm.r, IF(AND(ISNUMBER(_xlpm.q),_xlpm.q>0,ISNUMBER(_xlpm.u),_xlpm.u>0,ISNUMBER(_xlpm.d),_xlpm.d>=0,_xlpm.d<1), _xlpm.q*_xlpm.u*(1-_xlpm.d), "" ) ) ) -> 811.04 | K535: =_xlfn.LET( _xlpm.c,RawData!K535, _xlpm.r,RawData!J535, _xlpm.p,RawData!L535, IF(AND(ISNUMBER(_xlpm.c),_xlpm.c>=0),_xlpm.c, IF(AND(ISNUMBER(_xlpm.r),ISNUMBER(_xlpm.p)), _xlpm.r-_xlpm.p, "" ) ) ) -> 470.26 | L535: =_xlfn.LET( _xlpm.p,RawData!L535, _xlpm.r,RawData!J535, _xlpm.c,RawData!K535, IF(ISNUMBER(_xlpm.p),_xlpm.p, IF(AND(ISNUMBER(_xlpm.r),ISNUMBER(_xlpm.c)), _xlpm.r-_xlpm.c, "" ) )) -> 340.78
A536: ORD0535 | B536: 45953 | C536: =IF(RawData!C536="","Unknown",PROPER(TRIM(CLEAN(SUBSTITUTE(RawData!C536,CHAR(160)," "))))) -> North | D536: =IF(RawData!D536="","Unknown",PROPER(TRIM(CLEAN(SUBSTITUTE(RawData!D536,CHAR(160)," "))))) -> Jaipur | E536: =IF(RawData!E536="","Unknown",PROPER(TRIM(CLEAN(SUBSTITUTE(RawData!E536,CHAR(160)," "))))) -> Notebook | F536: =IF(RawData!F536="","Unknown",PROPER(TRIM(CLEAN(SUBSTITUTE(RawData!F536,CHAR(160)," "))))) -> Office Supplies | G536: =_xlfn.LET( _xlpm.q,RawData!G536, _xlpm.u,RawData!H536, _xlpm.d,RawData!I536, _xlpm.r,RawData!J536, IF(AND(ISNUMBER(_xlpm.q),_xlpm.q>0),_xlpm.q, IF(AND(ISNUMBER(_xlpm.r),ISNUMBER(_xlpm.u),_xlpm.u>0,ISNUMBER(_xlpm.d),_xlpm.d>=0,_xlpm.d<1), ROUND(_xlpm.r/(_xlpm.u*(1-_xlpm.d)),0), "" ) ) ) -> 3 | H536: =_xlfn.LET( _xlpm.q,RawData!G536, _xlpm.u,RawData!H536, _xlpm.d,RawData!I536, _xlpm.r,RawData!J536, IF(AND(ISNUMBER(_xlpm.u),_xlpm.u>0),_xlpm.u, IF(AND(ISNUMBER(_xlpm.q),_xlpm.q>0,ISNUMBER(_xlpm.r),ISNUMBER(_xlpm.d),_xlpm.d>=0,_xlpm.d<1), _xlpm.r/(_xlpm.q*(1-_xlpm.d)), "" ) ) ) -> 7.65 | I536: =_xlfn.LET( _xlpm.q,RawData!G536, _xlpm.u,RawData!H536, _xlpm.d,RawData!I536, _xlpm.r,RawData!J536, IF(AND(ISNUMBER(_xlpm.d),_xlpm.d>=0,_xlpm.d<1),_xlpm.d, IF(AND(ISNUMBER(_xlpm.q),_xlpm.q>0,ISNUMBER(_xlpm.u),_xlpm.u>0,ISNUMBER(_xlpm.r),_xlpm.r>=0), 1-(_xlpm.r/(_xlpm.q*_xlpm.u)), "" ) ) ) -> 0.05 | J536: =_xlfn.LET( _xlpm.q,RawData!G536, _xlpm.u,RawData!H536, _xlpm.d,RawData!I536, _xlpm.r,RawData!J536, IF(AND(ISNUMBER(_xlpm.r),_xlpm.r>=0),_xlpm.r, IF(AND(ISNUMBER(_xlpm.q),_xlpm.q>0,ISNUMBER(_xlpm.u),_xlpm.u>0,ISNUMBER(_xlpm.d),_xlpm.d>=0,_xlpm.d<1), _xlpm.q*_xlpm.u*(1-_xlpm.d), "" ) ) ) -> 21.8 | K536: =_xlfn.LET( _xlpm.c,RawData!K536, _xlpm.r,RawData!J536, _xlpm.p,RawData!L536, IF(AND(ISNUMBER(_xlpm.c),_xlpm.c>=0),_xlpm.c, IF(AND(ISNUMBER(_xlpm.r),ISNUMBER(_xlpm.p)), _xlpm.r-_xlpm.p, "" ) ) ) -> 13.68 | L536: =_xlfn.LET( _xlpm.p,RawData!L536, _xlpm.r,RawData!J536, _xlpm.c,RawData!K536, IF(ISNUMBER(_xlpm.p),_xlpm.p, IF(AND(ISNUMBER(_xlpm.r),ISNUMBER(_xlpm.c)), _xlpm.r-_xlpm.c, "" ) )) -> 8.12 | N536: =COUNTBLANK(H2:H601) -> 0
A537: ORD0536 | B537: 45758 | C537: =IF(RawData!C537="","Unknown",PROPER(TRIM(CLEAN(SUBSTITUTE(RawData!C537,CHAR(160)," "))))) -> West | D537: =IF(RawData!D537="","Unknown",PROPER(TRIM(CLEAN(SUBSTITUTE(RawData!D537,CHAR(160)," "))))) -> Pune | E537: =IF(RawData!E537="","Unknown",PROPER(TRIM(CLEAN(SUBSTITUTE(RawData!E537,CHAR(160)," "))))) -> Smartphone | F537: =IF(RawData!F537="","Unknown",PROPER(TRIM(CLEAN(SUBSTITUTE(RawData!F537,CHAR(160)," "))))) -> Electronics | G537: =_xlfn.LET( _xlpm.q,RawData!G537, _xlpm.u,RawData!H537, _xlpm.d,RawData!I537, _xlpm.r,RawData!J537, IF(AND(ISNUMBER(_xlpm.q),_xlpm.q>0),_xlpm.q, IF(AND(ISNUMBER(_xlpm.r),ISNUMBER(_xlpm.u),_xlpm.u>0,ISNUMBER(_xlpm.d),_xlpm.d>=0,_xlpm.d<1), ROUND(_xlpm.r/(_xlpm.u*(1-_xlpm.d)),0), "" ) ) ) -> 5 | H537: =_xlfn.LET( _xlpm.q,RawData!G537, _xlpm.u,RawData!H537, _xlpm.d,RawData!I537, _xlpm.r,RawData!J537, IF(AND(ISNUMBER(_xlpm.u),_xlpm.u>0),_xlpm.u, IF(AND(ISNUMBER(_xlpm.q),_xlpm.q>0,ISNUMBER(_xlpm.r),ISNUMBER(_xlpm.d),_xlpm.d>=0,_xlpm.d<1), _xlpm.r/(_xlpm.q*(1-_xlpm.d)), "" ) ) ) -> 516.39 | I537: =_xlfn.LET( _xlpm.q,RawData!G537, _xlpm.u,RawData!H537, _xlpm.d,RawData!I537, _xlpm.r,RawData!J537, IF(AND(ISNUMBER(_xlpm.d),_xlpm.d>=0,_xlpm.d<1),_xlpm.d, IF(AND(ISNUMBER(_xlpm.q),_xlpm.q>0,ISNUMBER(_xlpm.u),_xlpm.u>0,ISNUMBER(_xlpm.r),_xlpm.r>=0), 1-(_xlpm.r/(_xlpm.q*_xlpm.u)), "" ) ) ) -> 0.2 | J537: =_xlfn.LET( _xlpm.q,RawData!G537, _xlpm.u,RawData!H537, _xlpm.d,RawData!I537, _xlpm.r,RawData!J537, IF(AND(ISNUMBER(_xlpm.r),_xlpm.r>=0),_xlpm.r, IF(AND(ISNUMBER(_xlpm.q),_xlpm.q>0,ISNUMBER(_xlpm.u),_xlpm.u>0,ISNUMBER(_xlpm.d),_xlpm.d>=0,_xlpm.d<1), _xlpm.q*_xlpm.u*(1-_xlpm.d), "" ) ) ) -> 2065.56 | K537: =_xlfn.LET( _xlpm.c,RawData!K537, _xlpm.r,RawData!J537, _xlpm.p,RawData!L537, IF(AND(ISNUMBER(_xlpm.c),_xlpm.c>=0),_xlpm.c, IF(AND(ISNUMBER(_xlpm.r),ISNUMBER(_xlpm.p)), _xlpm.r-_xlpm.p, "" ) ) ) -> 1266.34 | L537: =_xlfn.LET( _xlpm.p,RawData!L537, _xlpm.r,RawData!J537, _xlpm.c,RawData!K537, IF(ISNUMBER(_xlpm.p),_xlpm.p, IF(AND(ISNUMBER(_xlpm.r),ISNUMBER(_xlpm.c)), _xlpm.r-_xlpm.c, "" ) )) -> 799.22
A538: ORD0537 | B538: 45928 | C538: =IF(RawData!C538="","Unknown",PROPER(TRIM(CLEAN(SUBSTITUTE(RawData!C538,CHAR(160)," "))))) -> East | D538: =IF(RawData!D538="","Unknown",PROPER(TRIM(CLEAN(SUBSTITUTE(RawData!D538,CHAR(160)," "))))) -> Bhubaneswar | E538: =IF(RawData!E538="","Unknown",PROPER(TRIM(CLEAN(SUBSTITUTE(RawData!E538,CHAR(160)," "))))) -> Pen Set | F538: =IF(RawData!F538="","Unknown",PROPER(TRIM(CLEAN(SUBSTITUTE(RawData!F538,CHAR(160)," "))))) -> Office Supplies | G538: =_xlfn.LET( _xlpm.q,RawData!G538, _xlpm.u,RawData!H538, _xlpm.d,RawData!I538, _xlpm.r,RawData!J538, IF(AND(ISNUMBER(_xlpm.q),_xlpm.q>0),_xlpm.q, IF(AND(ISNUMBER(_xlpm.r),ISNUMBER(_xlpm.u),_xlpm.u>0,ISNUMBER(_xlpm.d),_xlpm.d>=0,_xlpm.d<1), ROUND(_xlpm.r/(_xlpm.u*(1-_xlpm.d)),0), "" ) ) ) -> 7 | H538: =_xlfn.LET( _xlpm.q,RawData!G538, _xlpm.u,RawData!H538, _xlpm.d,RawData!I538, _xlpm.r,RawData!J538, IF(AND(ISNUMBER(_xlpm.u),_xlpm.u>0),_xlpm.u, IF(AND(ISNUMBER(_xlpm.q),_xlpm.q>0,ISNUMBER(_xlpm.r),ISNUMBER(_xlpm.d),_xlpm.d>=0,_xlpm.d<1), _xlpm.r/(_xlpm.q*(1-_xlpm.d)), "" ) ) ) -> 10.35 | I538: =_xlfn.LET( _xlpm.q,RawData!G538, _xlpm.u,RawData!H538, _xlpm.d,RawData!I538, _xlpm.r,RawData!J538, IF(AND(ISNUMBER(_xlpm.d),_xlpm.d>=0,_xlpm.d<1),_xlpm.d, IF(AND(ISNUMBER(_xlpm.q),_xlpm.q>0,ISNUMBER(_xlpm.u),_xlpm.u>0,ISNUMBER(_xlpm.r),_xlpm.r>=0), 1-(_xlpm.r/(_xlpm.q*_xlpm.u)), "" ) ) ) -> 0.15 | J538: =_xlfn.LET( _xlpm.q,RawData!G538, _xlpm.u,RawData!H538, _xlpm.d,RawData!I538, _xlpm.r,RawData!J538, IF(AND(ISNUMBER(_xlpm.r),_xlpm.r>=0),_xlpm.r, IF(AND(ISNUMBER(_xlpm.q),_xlpm.q>0,ISNUMBER(_xlpm.u),_xlpm.u>0,ISNUMBER(_xlpm.d),_xlpm.d>=0,_xlpm.d<1), _xlpm.q*_xlpm.u*(1-_xlpm.d), "" ) ) ) -> 61.58 | K538: =_xlfn.LET( _xlpm.c,RawData!K538, _xlpm.r,RawData!J538, _xlpm.p,RawData!L538, IF(AND(ISNUMBER(_xlpm.c),_xlpm.c>=0),_xlpm.c, IF(AND(ISNUMBER(_xlpm.r),ISNUMBER(_xlpm.p)), _xlpm.r-_xlpm.p, "" ) ) ) -> 34.17 | L538: =_xlfn.LET( _xlpm.p,RawData!L538, _xlpm.r,RawData!J538, _xlpm.c,RawData!K538, IF(ISNUMBER(_xlpm.p),_xlpm.p, IF(AND(ISNUMBER(_xlpm.r),ISNUMBER(_xlpm.c)), _xlpm.r-_xlpm.c, "" ) )) -> 27.41
A539: ORD0538 | B539: 45958 | C539: =IF(RawData!C539="","Unknown",PROPER(TRIM(CLEAN(SUBSTITUTE(RawData!C539,CHAR(160)," "))))) -> North | D539: =IF(RawData!D539="","Unknown",PROPER(TRIM(CLEAN(SUBSTITUTE(RawData!D539,CHAR(160)," "))))) -> Lucknow | E539: =IF(RawData!E539="","Unknown",PROPER(TRIM(CLEAN(SUBSTITUTE(RawData!E539,CHAR(160)," "))))) -> Desk | F539: =IF(RawData!F539="","Unknown",PROPER(TRIM(CLEAN(SUBSTITUTE(RawData!F539,CHAR(160)," "))))) -> Furniture | G539: =_xlfn.LET( _xlpm.q,RawData!G539, _xlpm.u,RawData!H539, _xlpm.d,RawData!I539, _xlpm.r,RawData!J539, IF(AND(ISNUMBER(_xlpm.q),_xlpm.q>0),_xlpm.q, IF(AND(ISNUMBER(_xlpm.r),ISNUMBER(_xlpm.u),_xlpm.u>0,ISNUMBER(_xlpm.d),_xlpm.d>=0,_xlpm.d<1), ROUND(_xlpm.r/(_xlpm.u*(1-_xlpm.d)),0), "" ) ) ) -> 6 | H539: =_xlfn.LET( _xlpm.q,RawData!G539, _xlpm.u,RawData!H539, _xlpm.d,RawData!I539, _xlpm.r,RawData!J539, IF(AND(ISNUMBER(_xlpm.u),_xlpm.u>0),_xlpm.u, IF(AND(ISNUMBER(_xlpm.q),_xlpm.q>0,ISNUMBER(_xlpm.r),ISNUMBER(_xlpm.d),_xlpm.d>=0,_xlpm.d<1), _xlpm.r/(_xlpm.q*(1-_xlpm.d)), "" ) ) ) -> 286.58 | I539: =_xlfn.LET( _xlpm.q,RawData!G539, _xlpm.u,RawData!H539, _xlpm.d,RawData!I539, _xlpm.r,RawData!J539, IF(AND(ISNUMBER(_xlpm.d),_xlpm.d>=0,_xlpm.d<1),_xlpm.d, IF(AND(ISNUMBER(_xlpm.q),_xlpm.q>0,ISNUMBER(_xlpm.u),_xlpm.u>0,ISNUMBER(_xlpm.r),_xlpm.r>=0), 1-(_xlpm.r/(_xlpm.q*_xlpm.u)), "" ) ) ) -> 0.1 | J539: =_xlfn.LET( _xlpm.q,RawData!G539, _xlpm.u,RawData!H539, _xlpm.d,RawData!I539, _xlpm.r,RawData!J539, IF(AND(ISNUMBER(_xlpm.r),_xlpm.r>=0),_xlpm.r, IF(AND(ISNUMBER(_xlpm.q),_xlpm.q>0,ISNUMBER(_xlpm.u),_xlpm.u>0,ISNUMBER(_xlpm.d),_xlpm.d>=0,_xlpm.d<1), _xlpm.q*_xlpm.u*(1-_xlpm.d), "" ) ) ) -> 1547.53 | K539: =_xlfn.LET( _xlpm.c,RawData!K539, _xlpm.r,RawData!J539, _xlpm.p,RawData!L539, IF(AND(ISNUMBER(_xlpm.c),_xlpm.c>=0),_xlpm.c, IF(AND(ISNUMBER(_xlpm.r),ISNUMBER(_xlpm.p)), _xlpm.r-_xlpm.p, "" ) ) ) -> 1029.88 | L539: =_xlfn.LET( _xlpm.p,RawData!L539, _xlpm.r,RawData!J539, _xlpm.c,RawData!K539, IF(ISNUMBER(_xlpm.p),_xlpm.p, IF(AND(ISNUMBER(_xlpm.r),ISNUMBER(_xlpm.c)), _xlpm.r-_xlpm.c, "" ) )) -> 517.65
A540: ORD0539 | B540: 45746 | C540: =IF(RawData!C540="","Unknown",PROPER(TRIM(CLEAN(SUBSTITUTE(RawData!C540,CHAR(160)," "))))) -> East | D540: =IF(RawData!D540="","Unknown",PROPER(TRIM(CLEAN(SUBSTITUTE(RawData!D540,CHAR(160)," "))))) -> Patna | E540: =IF(RawData!E540="","Unknown",PROPER(TRIM(CLEAN(SUBSTITUTE(RawData!E540,CHAR(160)," "))))) -> Pen Set | F540: =IF(RawData!F540="","Unknown",PROPER(TRIM(CLEAN(SUBSTITUTE(RawData!F540,CHAR(160)," "))))) -> Office Supplies | G540: =_xlfn.LET( _xlpm.q,RawData!G540, _xlpm.u,RawData!H540, _xlpm.d,RawData!I540, _xlpm.r,RawData!J540, IF(AND(ISNUMBER(_xlpm.q),_xlpm.q>0),_xlpm.q, IF(AND(ISNUMBER(_xlpm.r),ISNUMBER(_xlpm.u),_xlpm.u>0,ISNUMBER(_xlpm.d),_xlpm.d>=0,_xlpm.d<1), ROUND(_xlpm.r/(_xlpm.u*(1-_xlpm.d)),0), "" ) ) ) -> 10 | H540: =_xlfn.LET( _xlpm.q,RawData!G540, _xlpm.u,RawData!H540, _xlpm.d,RawData!I540, _xlpm.r,RawData!J540, IF(AND(ISNUMBER(_xlpm.u),_xlpm.u>0),_xlpm.u, IF(AND(ISNUMBER(_xlpm.q),_xlpm.q>0,ISNUMBER(_xlpm.r),ISNUMBER(_xlpm.d),_xlpm.d>=0,_xlpm.d<1), _xlpm.r/(_xlpm.q*(1-_xlpm.d)), "" ) ) ) -> 11.58 | I540: =_xlfn.LET( _xlpm.q,RawData!G540, _xlpm.u,RawData!H540, _xlpm.d,RawData!I540, _xlpm.r,RawData!J540, IF(AND(ISNUMBER(_xlpm.d),_xlpm.d>=0,_xlpm.d<1),_xlpm.d, IF(AND(ISNUMBER(_xlpm.q),_xlpm.q>0,ISNUMBER(_xlpm.u),_xlpm.u>0,ISNUMBER(_xlpm.r),_xlpm.r>=0), 1-(_xlpm.r/(_xlpm.q*_xlpm.u)), "" ) ) ) -> 0 | J540: =_xlfn.LET( _xlpm.q,RawData!G540, _xlpm.u,RawData!H540, _xlpm.d,RawData!I540, _xlpm.r,RawData!J540, IF(AND(ISNUMBER(_xlpm.r),_xlpm.r>=0),_xlpm.r, IF(AND(ISNUMBER(_xlpm.q),_xlpm.q>0,ISNUMBER(_xlpm.u),_xlpm.u>0,ISNUMBER(_xlpm.d),_xlpm.d>=0,_xlpm.d<1), _xlpm.q*_xlpm.u*(1-_xlpm.d), "" ) ) ) -> 115.8 | K540: =_xlfn.LET( _xlpm.c,RawData!K540, _xlpm.r,RawData!J540, _xlpm.p,RawData!L540, IF(AND(ISNUMBER(_xlpm.c),_xlpm.c>=0),_xlpm.c, IF(AND(ISNUMBER(_xlpm.r),ISNUMBER(_xlpm.p)), _xlpm.r-_xlpm.p, "" ) ) ) -> 84.94 | L540: =_xlfn.LET( _xlpm.p,RawData!L540, _xlpm.r,RawData!J540, _xlpm.c,RawData!K540, IF(ISNUMBER(_xlpm.p),_xlpm.p, IF(AND(ISNUMBER(_xlpm.r),ISNUMBER(_xlpm.c)), _xlpm.r-_xlpm.c, "" ) )) -> 30.86
A541: ORD0540 | B541: 45726 | C541: =IF(RawData!C541="","Unknown",PROPER(TRIM(CLEAN(SUBSTITUTE(RawData!C541,CHAR(160)," "))))) -> East | D541: =IF(RawData!D541="","Unknown",PROPER(TRIM(CLEAN(SUBSTITUTE(RawData!D541,CHAR(160)," "))))) -> Kolkata | E541: =IF(RawData!E541="","Unknown",PROPER(TRIM(CLEAN(SUBSTITUTE(RawData!E541,CHAR(160)," "))))) -> Smartphone | F541: =IF(RawData!F541="","Unknown",PROPER(TRIM(CLEAN(SUBSTITUTE(RawData!F541,CHAR(160)," "))))) -> Electronics | G541: =_xlfn.LET( _xlpm.q,RawData!G541, _xlpm.u,RawData!H541, _xlpm.d,RawData!I541, _xlpm.r,RawData!J541, IF(AND(ISNUMBER(_xlpm.q),_xlpm.q>0),_xlpm.q, IF(AND(ISNUMBER(_xlpm.r),ISNUMBER(_xlpm.u),_xlpm.u>0,ISNUMBER(_xlpm.d),_xlpm.d>=0,_xlpm.d<1), ROUND(_xlpm.r/(_xlpm.u*(1-_xlpm.d)),0), "" ) ) ) -> 4 | H541: =_xlfn.LET( _xlpm.q,RawData!G541, _xlpm.u,RawData!H541, _xlpm.d,RawData!I541, _xlpm.r,RawData!J541, IF(AND(ISNUMBER(_xlpm.u),_xlpm.u>0),_xlpm.u, IF(AND(ISNUMBER(_xlpm.q),_xlpm.q>0,ISNUMBER(_xlpm.r),ISNUMBER(_xlpm.d),_xlpm.d>=0,_xlpm.d<1), _xlpm.r/(_xlpm.q*(1-_xlpm.d)), "" ) ) ) -> 503.51 | I541: =_xlfn.LET( _xlpm.q,RawData!G541, _xlpm.u,RawData!H541, _xlpm.d,RawData!I541, _xlpm.r,RawData!J541, IF(AND(ISNUMBER(_xlpm.d),_xlpm.d>=0,_xlpm.d<1),_xlpm.d, IF(AND(ISNUMBER(_xlpm.q),_xlpm.q>0,ISNUMBER(_xlpm.u),_xlpm.u>0,ISNUMBER(_xlpm.r),_xlpm.r>=0), 1-(_xlpm.r/(_xlpm.q*_xlpm.u)), "" ) ) ) -> 0.05 | J541: =_xlfn.LET( _xlpm.q,RawData!G541, _xlpm.u,RawData!H541, _xlpm.d,RawData!I541, _xlpm.r,RawData!J541, IF(AND(ISNUMBER(_xlpm.r),_xlpm.r>=0),_xlpm.r, IF(AND(ISNUMBER(_xlpm.q),_xlpm.q>0,ISNUMBER(_xlpm.u),_xlpm.u>0,ISNUMBER(_xlpm.d),_xlpm.d>=0,_xlpm.d<1), _xlpm.q*_xlpm.u*(1-_xlpm.d), "" ) ) ) -> 1913.34 | K541: =_xlfn.LET( _xlpm.c,RawData!K541, _xlpm.r,RawData!J541, _xlpm.p,RawData!L541, IF(AND(ISNUMBER(_xlpm.c),_xlpm.c>=0),_xlpm.c, IF(AND(ISNUMBER(_xlpm.r),ISNUMBER(_xlpm.p)), _xlpm.r-_xlpm.p, "" ) ) ) -> 1543.09 | L541: =_xlfn.LET( _xlpm.p,RawData!L541, _xlpm.r,RawData!J541, _xlpm.c,RawData!K541, IF(ISNUMBER(_xlpm.p),_xlpm.p, IF(AND(ISNUMBER(_xlpm.r),ISNUMBER(_xlpm.c)), _xlpm.r-_xlpm.c, "" ) )) -> 370.25
A542: ORD0541 | B542: 45751 | C542: =IF(RawData!C542="","Unknown",PROPER(TRIM(CLEAN(SUBSTITUTE(RawData!C542,CHAR(160)," "))))) -> East | D542: =IF(RawData!D542="","Unknown",PROPER(TRIM(CLEAN(SUBSTITUTE(RawData!D542,CHAR(160)," "))))) -> Bhubaneswar | E542: =IF(RawData!E542="","Unknown",PROPER(TRIM(CLEAN(SUBSTITUTE(RawData!E542,CHAR(160)," "))))) -> Keyboard | F542: =IF(RawData!F542="","Unknown",PROPER(TRIM(CLEAN(SUBSTITUTE(RawData!F542,CHAR(160)," "))))) -> Accessories | G542: =_xlfn.LET( _xlpm.q,RawData!G542, _xlpm.u,RawData!H542, _xlpm.d,RawData!I542, _xlpm.r,RawData!J542, IF(AND(ISNUMBER(_xlpm.q),_xlpm.q>0),_xlpm.q, IF(AND(ISNUMBER(_xlpm.r),ISNUMBER(_xlpm.u),_xlpm.u>0,ISNUMBER(_xlpm.d),_xlpm.d>=0,_xlpm.d<1), ROUND(_xlpm.r/(_xlpm.u*(1-_xlpm.d)),0), "" ) ) ) -> 3 | H542: =_xlfn.LET( _xlpm.q,RawData!G542, _xlpm.u,RawData!H542, _xlpm.d,RawData!I542, _xlpm.r,RawData!J542, IF(AND(ISNUMBER(_xlpm.u),_xlpm.u>0),_xlpm.u, IF(AND(ISNUMBER(_xlpm.q),_xlpm.q>0,ISNUMBER(_xlpm.r),ISNUMBER(_xlpm.d),_xlpm.d>=0,_xlpm.d<1), _xlpm.r/(_xlpm.q*(1-_xlpm.d)), "" ) ) ) -> 38.01 | I542: =_xlfn.LET( _xlpm.q,RawData!G542, _xlpm.u,RawData!H542, _xlpm.d,RawData!I542, _xlpm.r,RawData!J542, IF(AND(ISNUMBER(_xlpm.d),_xlpm.d>=0,_xlpm.d<1),_xlpm.d, IF(AND(ISNUMBER(_xlpm.q),_xlpm.q>0,ISNUMBER(_xlpm.u),_xlpm.u>0,ISNUMBER(_xlpm.r),_xlpm.r>=0), 1-(_xlpm.r/(_xlpm.q*_xlpm.u)), "" ) ) ) -> 0.15 | J542: =_xlfn.LET( _xlpm.q,RawData!G542, _xlpm.u,RawData!H542, _xlpm.d,RawData!I542, _xlpm.r,RawData!J542, IF(AND(ISNUMBER(_xlpm.r),_xlpm.r>=0),_xlpm.r, IF(AND(ISNUMBER(_xlpm.q),_xlpm.q>0,ISNUMBER(_xlpm.u),_xlpm.u>0,ISNUMBER(_xlpm.d),_xlpm.d>=0,_xlpm.d<1), _xlpm.q*_xlpm.u*(1-_xlpm.d), "" ) ) ) -> 96.93 | K542: =_xlfn.LET( _xlpm.c,RawData!K542, _xlpm.r,RawData!J542, _xlpm.p,RawData!L542, IF(AND(ISNUMBER(_xlpm.c),_xlpm.c>=0),_xlpm.c, IF(AND(ISNUMBER(_xlpm.r),ISNUMBER(_xlpm.p)), _xlpm.r-_xlpm.p, "" ) ) ) -> 55.65 | L542: =_xlfn.LET( _xlpm.p,RawData!L542, _xlpm.r,RawData!J542, _xlpm.c,RawData!K542, IF(ISNUMBER(_xlpm.p),_xlpm.p, IF(AND(ISNUMBER(_xlpm.r),ISNUMBER(_xlpm.c)), _xlpm.r-_xlpm.c, "" ) )) -> 41.28
A543: ORD0542 | B543: 45872 | C543: =IF(RawData!C543="","Unknown",PROPER(TRIM(CLEAN(SUBSTITUTE(RawData!C543,CHAR(160)," "))))) -> South | D543: =IF(RawData!D543="","Unknown",PROPER(TRIM(CLEAN(SUBSTITUTE(RawData!D543,CHAR(160)," "))))) -> Hyderabad | E543: =IF(RawData!E543="","Unknown",PROPER(TRIM(CLEAN(SUBSTITUTE(RawData!E543,CHAR(160)," "))))) -> Pen Set | F543: =IF(RawData!F543="","Unknown",PROPER(TRIM(CLEAN(SUBSTITUTE(RawData!F543,CHAR(160)," "))))) -> Office Supplies | G543: =_xlfn.LET( _xlpm.q,RawData!G543, _xlpm.u,RawData!H543, _xlpm.d,RawData!I543, _xlpm.r,RawData!J543, IF(AND(ISNUMBER(_xlpm.q),_xlpm.q>0),_xlpm.q, IF(AND(ISNUMBER(_xlpm.r),ISNUMBER(_xlpm.u),_xlpm.u>0,ISNUMBER(_xlpm.d),_xlpm.d>=0,_xlpm.d<1), ROUND(_xlpm.r/(_xlpm.u*(1-_xlpm.d)),0), "" ) ) ) -> 7 | H543: =_xlfn.LET( _xlpm.q,RawData!G543, _xlpm.u,RawData!H543, _xlpm.d,RawData!I543, _xlpm.r,RawData!J543, IF(AND(ISNUMBER(_xlpm.u),_xlpm.u>0),_xlpm.u, IF(AND(ISNUMBER(_xlpm.q),_xlpm.q>0,ISNUMBER(_xlpm.r),ISNUMBER(_xlpm.d),_xlpm.d>=0,_xlpm.d<1), _xlpm.r/(_xlpm.q*(1-_xlpm.d)), "" ) ) ) -> 11.7 | I543: =_xlfn.LET( _xlpm.q,RawData!G543, _xlpm.u,RawData!H543, _xlpm.d,RawData!I543, _xlpm.r,RawData!J543, IF(AND(ISNUMBER(_xlpm.d),_xlpm.d>=0,_xlpm.d<1),_xlpm.d, IF(AND(ISNUMBER(_xlpm.q),_xlpm.q>0,ISNUMBER(_xlpm.u),_xlpm.u>0,ISNUMBER(_xlpm.r),_xlpm.r>=0), 1-(_xlpm.r/(_xlpm.q*_xlpm.u)), "" ) ) ) -> 0.1 | J543: =_xlfn.LET( _xlpm.q,RawData!G543, _xlpm.u,RawData!H543, _xlpm.d,RawData!I543, _xlpm.r,RawData!J543, IF(AND(ISNUMBER(_xlpm.r),_xlpm.r>=0),_xlpm.r, IF(AND(ISNUMBER(_xlpm.q),_xlpm.q>0,ISNUMBER(_xlpm.u),_xlpm.u>0,ISNUMBER(_xlpm.d),_xlpm.d>=0,_xlpm.d<1), _xlpm.q*_xlpm.u*(1-_xlpm.d), "" ) ) ) -> 73.71 | K543: =_xlfn.LET( _xlpm.c,RawData!K543, _xlpm.r,RawData!J543, _xlpm.p,RawData!L543, IF(AND(ISNUMBER(_xlpm.c),_xlpm.c>=0),_xlpm.c, IF(AND(ISNUMBER(_xlpm.r),ISNUMBER(_xlpm.p)), _xlpm.r-_xlpm.p, "" ) ) ) -> 58.04 | L543: =_xlfn.LET( _xlpm.p,RawData!L543, _xlpm.r,RawData!J543, _xlpm.c,RawData!K543, IF(ISNUMBER(_xlpm.p),_xlpm.p, IF(AND(ISNUMBER(_xlpm.r),ISNUMBER(_xlpm.c)), _xlpm.r-_xlpm.c, "" ) )) -> 15.67
A544: ORD0543 | B544: 45907 | C544: =IF(RawData!C544="","Unknown",PROPER(TRIM(CLEAN(SUBSTITUTE(RawData!C544,CHAR(160)," "))))) -> South | D544: =IF(RawData!D544="","Unknown",PROPER(TRIM(CLEAN(SUBSTITUTE(RawData!D544,CHAR(160)," "))))) -> Chennai | E544: =IF(RawData!E544="","Unknown",PROPER(TRIM(CLEAN(SUBSTITUTE(RawData!E544,CHAR(160)," "))))) -> Notebook | F544: =IF(RawData!F544="","Unknown",PROPER(TRIM(CLEAN(SUBSTITUTE(RawData!F544,CHAR(160)," "))))) -> Office Supplies | G544: =_xlfn.LET( _xlpm.q,RawData!G544, _xlpm.u,RawData!H544, _xlpm.d,RawData!I544, _xlpm.r,RawData!J544, IF(AND(ISNUMBER(_xlpm.q),_xlpm.q>0),_xlpm.q, IF(AND(ISNUMBER(_xlpm.r),ISNUMBER(_xlpm.u),_xlpm.u>0,ISNUMBER(_xlpm.d),_xlpm.d>=0,_xlpm.d<1), ROUND(_xlpm.r/(_xlpm.u*(1-_xlpm.d)),0), "" ) ) ) -> 3 | H544: =_xlfn.LET( _xlpm.q,RawData!G544, _xlpm.u,RawData!H544, _xlpm.d,RawData!I544, _xlpm.r,RawData!J544, IF(AND(ISNUMBER(_xlpm.u),_xlpm.u>0),_xlpm.u, IF(AND(ISNUMBER(_xlpm.q),_xlpm.q>0,ISNUMBER(_xlpm.r),ISNUMBER(_xlpm.d),_xlpm.d>=0,_xlpm.d<1), _xlpm.r/(_xlpm.q*(1-_xlpm.d)), "" ) ) ) -> 9.07 | I544: =_xlfn.LET( _xlpm.q,RawData!G544, _xlpm.u,RawData!H544, _xlpm.d,RawData!I544, _xlpm.r,RawData!J544, IF(AND(ISNUMBER(_xlpm.d),_xlpm.d>=0,_xlpm.d<1),_xlpm.d, IF(AND(ISNUMBER(_xlpm.q),_xlpm.q>0,ISNUMBER(_xlpm.u),_xlpm.u>0,ISNUMBER(_xlpm.r),_xlpm.r>=0), 1-(_xlpm.r/(_xlpm.q*_xlpm.u)), "" ) ) ) -> 0.1 | J544: =_xlfn.LET( _xlpm.q,RawData!G544, _xlpm.u,RawData!H544, _xlpm.d,RawData!I544, _xlpm.r,RawData!J544, IF(AND(ISNUMBER(_xlpm.r),_xlpm.r>=0),_xlpm.r, IF(AND(ISNUMBER(_xlpm.q),_xlpm.q>0,ISNUMBER(_xlpm.u),_xlpm.u>0,ISNUMBER(_xlpm.d),_xlpm.d>=0,_xlpm.d<1), _xlpm.q*_xlpm.u*(1-_xlpm.d), "" ) ) ) -> 24.49 | K544: =_xlfn.LET( _xlpm.c,RawData!K544, _xlpm.r,RawData!J544, _xlpm.p,RawData!L544, IF(AND(ISNUMBER(_xlpm.c),_xlpm.c>=0),_xlpm.c, IF(AND(ISNUMBER(_xlpm.r),ISNUMBER(_xlpm.p)), _xlpm.r-_xlpm.p, "" ) ) ) -> 16.56 | L544: =_xlfn.LET( _xlpm.p,RawData!L544, _xlpm.r,RawData!J544, _xlpm.c,RawData!K544, IF(ISNUMBER(_xlpm.p),_xlpm.p, IF(AND(ISNUMBER(_xlpm.r),ISNUMBER(_xlpm.c)), _xlpm.r-_xlpm.c, "" ) )) -> 7.93
A545: ORD0544 | B545: 45729 | C545: =IF(RawData!C545="","Unknown",PROPER(TRIM(CLEAN(SUBSTITUTE(RawData!C545,CHAR(160)," "))))) -> South | D545: =IF(RawData!D545="","Unknown",PROPER(TRIM(CLEAN(SUBSTITUTE(RawData!D545,CHAR(160)," "))))) -> Hyderabad | E545: =IF(RawData!E545="","Unknown",PROPER(TRIM(CLEAN(SUBSTITUTE(RawData!E545,CHAR(160)," "))))) -> Desk | F545: =IF(RawData!F545="","Unknown",PROPER(TRIM(CLEAN(SUBSTITUTE(RawData!F545,CHAR(160)," "))))) -> Furniture | G545: =_xlfn.LET( _xlpm.q,RawData!G545, _xlpm.u,RawData!H545, _xlpm.d,RawData!I545, _xlpm.r,RawData!J545, IF(AND(ISNUMBER(_xlpm.q),_xlpm.q>0),_xlpm.q, IF(AND(ISNUMBER(_xlpm.r),ISNUMBER(_xlpm.u),_xlpm.u>0,ISNUMBER(_xlpm.d),_xlpm.d>=0,_xlpm.d<1), ROUND(_xlpm.r/(_xlpm.u*(1-_xlpm.d)),0), "" ) ) ) -> 8 | H545: =_xlfn.LET( _xlpm.q,RawData!G545, _xlpm.u,RawData!H545, _xlpm.d,RawData!I545, _xlpm.r,RawData!J545, IF(AND(ISNUMBER(_xlpm.u),_xlpm.u>0),_xlpm.u, IF(AND(ISNUMBER(_xlpm.q),_xlpm.q>0,ISNUMBER(_xlpm.r),ISNUMBER(_xlpm.d),_xlpm.d>=0,_xlpm.d<1), _xlpm.r/(_xlpm.q*(1-_xlpm.d)), "" ) ) ) -> 258.51 | I545: =_xlfn.LET( _xlpm.q,RawData!G545, _xlpm.u,RawData!H545, _xlpm.d,RawData!I545, _xlpm.r,RawData!J545, IF(AND(ISNUMBER(_xlpm.d),_xlpm.d>=0,_xlpm.d<1),_xlpm.d, IF(AND(ISNUMBER(_xlpm.q),_xlpm.q>0,ISNUMBER(_xlpm.u),_xlpm.u>0,ISNUMBER(_xlpm.r),_xlpm.r>=0), 1-(_xlpm.r/(_xlpm.q*_xlpm.u)), "" ) ) ) -> 0.15 | J545: =_xlfn.LET( _xlpm.q,RawData!G545, _xlpm.u,RawData!H545, _xlpm.d,RawData!I545, _xlpm.r,RawData!J545, IF(AND(ISNUMBER(_xlpm.r),_xlpm.r>=0),_xlpm.r, IF(AND(ISNUMBER(_xlpm.q),_xlpm.q>0,ISNUMBER(_xlpm.u),_xlpm.u>0,ISNUMBER(_xlpm.d),_xlpm.d>=0,_xlpm.d<1), _xlpm.q*_xlpm.u*(1-_xlpm.d), "" ) ) ) -> 1757.87 | K545: =_xlfn.LET( _xlpm.c,RawData!K545, _xlpm.r,RawData!J545, _xlpm.p,RawData!L545, IF(AND(ISNUMBER(_xlpm.c),_xlpm.c>=0),_xlpm.c, IF(AND(ISNUMBER(_xlpm.r),ISNUMBER(_xlpm.p)), _xlpm.r-_xlpm.p, "" ) ) ) -> 1046.11 | L545: =_xlfn.LET( _xlpm.p,RawData!L545, _xlpm.r,RawData!J545, _xlpm.c,RawData!K545, IF(ISNUMBER(_xlpm.p),_xlpm.p, IF(AND(ISNUMBER(_xlpm.r),ISNUMBER(_xlpm.c)), _xlpm.r-_xlpm.c, "" ) )) -> 711.76
A546: ORD0545 | B546: 45841 | C546: =IF(RawData!C546="","Unknown",PROPER(TRIM(CLEAN(SUBSTITUTE(RawData!C546,CHAR(160)," "))))) -> North | D546: =IF(RawData!D546="","Unknown",PROPER(TRIM(CLEAN(SUBSTITUTE(RawData!D546,CHAR(160)," "))))) -> Jaipur | E546: =IF(RawData!E546="","Unknown",PROPER(TRIM(CLEAN(SUBSTITUTE(RawData!E546,CHAR(160)," "))))) -> Printer | F546: =IF(RawData!F546="","Unknown",PROPER(TRIM(CLEAN(SUBSTITUTE(RawData!F546,CHAR(160)," "))))) -> Office Supplies | G546: =_xlfn.LET( _xlpm.q,RawData!G546, _xlpm.u,RawData!H546, _xlpm.d,RawData!I546, _xlpm.r,RawData!J546, IF(AND(ISNUMBER(_xlpm.q),_xlpm.q>0),_xlpm.q, IF(AND(ISNUMBER(_xlpm.r),ISNUMBER(_xlpm.u),_xlpm.u>0,ISNUMBER(_xlpm.d),_xlpm.d>=0,_xlpm.d<1), ROUND(_xlpm.r/(_xlpm.u*(1-_xlpm.d)),0), "" ) ) ) -> 3 | H546: =_xlfn.LET( _xlpm.q,RawData!G546, _xlpm.u,RawData!H546, _xlpm.d,RawData!I546, _xlpm.r,RawData!J546, IF(AND(ISNUMBER(_xlpm.u),_xlpm.u>0),_xlpm.u, IF(AND(ISNUMBER(_xlpm.q),_xlpm.q>0,ISNUMBER(_xlpm.r),ISNUMBER(_xlpm.d),_xlpm.d>=0,_xlpm.d<1), _xlpm.r/(_xlpm.q*(1-_xlpm.d)), "" ) ) ) -> 183.58 | I546: =_xlfn.LET( _xlpm.q,RawData!G546, _xlpm.u,RawData!H546, _xlpm.d,RawData!I546, _xlpm.r,RawData!J546, IF(AND(ISNUMBER(_xlpm.d),_xlpm.d>=0,_xlpm.d<1),_xlpm.d, IF(AND(ISNUMBER(_xlpm.q),_xlpm.q>0,ISNUMBER(_xlpm.u),_xlpm.u>0,ISNUMBER(_xlpm.r),_xlpm.r>=0), 1-(_xlpm.r/(_xlpm.q*_xlpm.u)), "" ) ) ) -> 0.02 | J546: =_xlfn.LET( _xlpm.q,RawData!G546, _xlpm.u,RawData!H546, _xlpm.d,RawData!I546, _xlpm.r,RawData!J546, IF(AND(ISNUMBER(_xlpm.r),_xlpm.r>=0),_xlpm.r, IF(AND(ISNUMBER(_xlpm.q),_xlpm.q>0,ISNUMBER(_xlpm.u),_xlpm.u>0,ISNUMBER(_xlpm.d),_xlpm.d>=0,_xlpm.d<1), _xlpm.q*_xlpm.u*(1-_xlpm.d), "" ) ) ) -> 539.73 | K546: =_xlfn.LET( _xlpm.c,RawData!K546, _xlpm.r,RawData!J546, _xlpm.p,RawData!L546, IF(AND(ISNUMBER(_xlpm.c),_xlpm.c>=0),_xlpm.c, IF(AND(ISNUMBER(_xlpm.r),ISNUMBER(_xlpm.p)), _xlpm.r-_xlpm.p, "" ) ) ) -> 330.61 | L546: =_xlfn.LET( _xlpm.p,RawData!L546, _xlpm.r,RawData!J546, _xlpm.c,RawData!K546, IF(ISNUMBER(_xlpm.p),_xlpm.p, IF(AND(ISNUMBER(_xlpm.r),ISNUMBER(_xlpm.c)), _xlpm.r-_xlpm.c, "" ) )) -> 209.12
A547: ORD0546 | B547: 45945 | C547: =IF(RawData!C547="","Unknown",PROPER(TRIM(CLEAN(SUBSTITUTE(RawData!C547,CHAR(160)," "))))) -> West | D547: =IF(RawData!D547="","Unknown",PROPER(TRIM(CLEAN(SUBSTITUTE(RawData!D547,CHAR(160)," "))))) -> Ahmedabad | E547: =IF(RawData!E547="","Unknown",PROPER(TRIM(CLEAN(SUBSTITUTE(RawData!E547,CHAR(160)," "))))) -> Bookshelf | F547: =IF(RawData!F547="","Unknown",PROPER(TRIM(CLEAN(SUBSTITUTE(RawData!F547,CHAR(160)," "))))) -> Furniture | G547: =_xlfn.LET( _xlpm.q,RawData!G547, _xlpm.u,RawData!H547, _xlpm.d,RawData!I547, _xlpm.r,RawData!J547, IF(AND(ISNUMBER(_xlpm.q),_xlpm.q>0),_xlpm.q, IF(AND(ISNUMBER(_xlpm.r),ISNUMBER(_xlpm.u),_xlpm.u>0,ISNUMBER(_xlpm.d),_xlpm.d>=0,_xlpm.d<1), ROUND(_xlpm.r/(_xlpm.u*(1-_xlpm.d)),0), "" ) ) ) -> 8 | H547: =_xlfn.LET( _xlpm.q,RawData!G547, _xlpm.u,RawData!H547, _xlpm.d,RawData!I547, _xlpm.r,RawData!J547, IF(AND(ISNUMBER(_xlpm.u),_xlpm.u>0),_xlpm.u, IF(AND(ISNUMBER(_xlpm.q),_xlpm.q>0,ISNUMBER(_xlpm.r),ISNUMBER(_xlpm.d),_xlpm.d>=0,_xlpm.d<1), _xlpm.r/(_xlpm.q*(1-_xlpm.d)), "" ) ) ) -> 158.59 | I547: =_xlfn.LET( _xlpm.q,RawData!G547, _xlpm.u,RawData!H547, _xlpm.d,RawData!I547, _xlpm.r,RawData!J547, IF(AND(ISNUMBER(_xlpm.d),_xlpm.d>=0,_xlpm.d<1),_xlpm.d, IF(AND(ISNUMBER(_xlpm.q),_xlpm.q>0,ISNUMBER(_xlpm.u),_xlpm.u>0,ISNUMBER(_xlpm.r),_xlpm.r>=0), 1-(_xlpm.r/(_xlpm.q*_xlpm.u)), "" ) ) ) -> 0.1 | J547: =_xlfn.LET( _xlpm.q,RawData!G547, _xlpm.u,RawData!H547, _xlpm.d,RawData!I547, _xlpm.r,RawData!J547, IF(AND(ISNUMBER(_xlpm.r),_xlpm.r>=0),_xlpm.r, IF(AND(ISNUMBER(_xlpm.q),_xlpm.q>0,ISNUMBER(_xlpm.u),_xlpm.u>0,ISNUMBER(_xlpm.d),_xlpm.d>=0,_xlpm.d<1), _xlpm.q*_xlpm.u*(1-_xlpm.d), "" ) ) ) -> 1141.85 | K547: =_xlfn.LET( _xlpm.c,RawData!K547, _xlpm.r,RawData!J547, _xlpm.p,RawData!L547, IF(AND(ISNUMBER(_xlpm.c),_xlpm.c>=0),_xlpm.c, IF(AND(ISNUMBER(_xlpm.r),ISNUMBER(_xlpm.p)), _xlpm.r-_xlpm.p, "" ) ) ) -> 828.3 | L547: =_xlfn.LET( _xlpm.p,RawData!L547, _xlpm.r,RawData!J547, _xlpm.c,RawData!K547, IF(ISNUMBER(_xlpm.p),_xlpm.p, IF(AND(ISNUMBER(_xlpm.r),ISNUMBER(_xlpm.c)), _xlpm.r-_xlpm.c, "" ) )) -> 313.55
A548: ORD0547 | B548: 45885 | C548: =IF(RawData!C548="","Unknown",PROPER(TRIM(CLEAN(SUBSTITUTE(RawData!C548,CHAR(160)," "))))) -> West | D548: =IF(RawData!D548="","Unknown",PROPER(TRIM(CLEAN(SUBSTITUTE(RawData!D548,CHAR(160)," "))))) -> Mumbai | E548: =IF(RawData!E548="","Unknown",PROPER(TRIM(CLEAN(SUBSTITUTE(RawData!E548,CHAR(160)," "))))) -> Headphones | F548: =IF(RawData!F548="","Unknown",PROPER(TRIM(CLEAN(SUBSTITUTE(RawData!F548,CHAR(160)," "))))) -> Electronics | G548: =_xlfn.LET( _xlpm.q,RawData!G548, _xlpm.u,RawData!H548, _xlpm.d,RawData!I548, _xlpm.r,RawData!J548, IF(AND(ISNUMBER(_xlpm.q),_xlpm.q>0),_xlpm.q, IF(AND(ISNUMBER(_xlpm.r),ISNUMBER(_xlpm.u),_xlpm.u>0,ISNUMBER(_xlpm.d),_xlpm.d>=0,_xlpm.d<1), ROUND(_xlpm.r/(_xlpm.u*(1-_xlpm.d)),0), "" ) ) ) -> 2 | H548: =_xlfn.LET( _xlpm.q,RawData!G548, _xlpm.u,RawData!H548, _xlpm.d,RawData!I548, _xlpm.r,RawData!J548, IF(AND(ISNUMBER(_xlpm.u),_xlpm.u>0),_xlpm.u, IF(AND(ISNUMBER(_xlpm.q),_xlpm.q>0,ISNUMBER(_xlpm.r),ISNUMBER(_xlpm.d),_xlpm.d>=0,_xlpm.d<1), _xlpm.r/(_xlpm.q*(1-_xlpm.d)), "" ) ) ) -> 82.59 | I548: =_xlfn.LET( _xlpm.q,RawData!G548, _xlpm.u,RawData!H548, _xlpm.d,RawData!I548, _xlpm.r,RawData!J548, IF(AND(ISNUMBER(_xlpm.d),_xlpm.d>=0,_xlpm.d<1),_xlpm.d, IF(AND(ISNUMBER(_xlpm.q),_xlpm.q>0,ISNUMBER(_xlpm.u),_xlpm.u>0,ISNUMBER(_xlpm.r),_xlpm.r>=0), 1-(_xlpm.r/(_xlpm.q*_xlpm.u)), "" ) ) ) -> 0.15 | J548: =_xlfn.LET( _xlpm.q,RawData!G548, _xlpm.u,RawData!H548, _xlpm.d,RawData!I548, _xlpm.r,RawData!J548, IF(AND(ISNUMBER(_xlpm.r),_xlpm.r>=0),_xlpm.r, IF(AND(ISNUMBER(_xlpm.q),_xlpm.q>0,ISNUMBER(_xlpm.u),_xlpm.u>0,ISNUMBER(_xlpm.d),_xlpm.d>=0,_xlpm.d<1), _xlpm.q*_xlpm.u*(1-_xlpm.d), "" ) ) ) -> 140.4 | K548: =_xlfn.LET( _xlpm.c,RawData!K548, _xlpm.r,RawData!J548, _xlpm.p,RawData!L548, IF(AND(ISNUMBER(_xlpm.c),_xlpm.c>=0),_xlpm.c, IF(AND(ISNUMBER(_xlpm.r),ISNUMBER(_xlpm.p)), _xlpm.r-_xlpm.p, "" ) ) ) -> 96.65 | L548: =_xlfn.LET( _xlpm.p,RawData!L548, _xlpm.r,RawData!J548, _xlpm.c,RawData!K548, IF(ISNUMBER(_xlpm.p),_xlpm.p, IF(AND(ISNUMBER(_xlpm.r),ISNUMBER(_xlpm.c)), _xlpm.r-_xlpm.c, "" ) )) -> 43.75
... A601: ORD0600 | B601: 45835 | C601: =IF(RawData!C601="","Unknown",PROPER(TRIM(CLEAN(SUBSTITUTE(RawData!C601,CHAR(160)," "))))) -> East | D601: =IF(RawData!D601="","Unknown",PROPER(TRIM(CLEAN(SUBSTITUTE(RawData!D601,CHAR(160)," "))))) -> Patna | E601: =IF(RawData!E601="","Unknown",PROPER(TRIM(CLEAN(SUBSTITUTE(RawData!E601,CHAR(160)," "))))) -> Headphones | F601: =IF(RawData!F601="","Unknown",PROPER(TRIM(CLEAN(SUBSTITUTE(RawData!F601,CHAR(160)," "))))) -> Electronics | G601: =_xlfn.LET( _xlpm.q,RawData!G601, _xlpm.u,RawData!H601, _xlpm.d,RawData!I601, _xlpm.r,RawData!J601, IF(AND(ISNUMBER(_xlpm.q),_xlpm.q>0),_xlpm.q, IF(AND(ISNUMBER(_xlpm.r),ISNUMBER(_xlpm.u),_xlpm.u>0,ISNUMBER(_xlpm.d),_xlpm.d>=0,_xlpm.d<1), ROUND(_xlpm.r/(_xlpm.u*(1-_xlpm.d)),0), "" ) ) ) -> 6 | H601: =_xlfn.LET( _xlpm.q,RawData!G601, _xlpm.u,RawData!H601, _xlpm.d,RawData!I601, _xlpm.r,RawData!J601, IF(AND(ISNUMBER(_xlpm.u),_xlpm.u>0),_xlpm.u, IF(AND(ISNUMBER(_xlpm.q),_xlpm.q>0,ISNUMBER(_xlpm.r),ISNUMBER(_xlpm.d),_xlpm.d>=0,_xlpm.d<1), _xlpm.r/(_xlpm.q*(1-_xlpm.d)), "" ) ) ) -> 85.99 | I601: =_xlfn.LET( _xlpm.q,RawData!G601, _xlpm.u,RawData!H601, _xlpm.d,RawData!I601, _xlpm.r,RawData!J601, IF(AND(ISNUMBER(_xlpm.d),_xlpm.d>=0,_xlpm.d<1),_xlpm.d, IF(AND(ISNUMBER(_xlpm.q),_xlpm.q>0,ISNUMBER(_xlpm.u),_xlpm.u>0,ISNUMBER(_xlpm.r),_xlpm.r>=0), 1-(_xlpm.r/(_xlpm.q*_xlpm.u)), "" ) ) ) -> 0.02 | J601: =_xlfn.LET( _xlpm.q,RawData!G601, _xlpm.u,RawData!H601, _xlpm.d,RawData!I601, _xlpm.r,RawData!J601, IF(AND(ISNUMBER(_xlpm.r),_xlpm.r>=0),_xlpm.r, IF(AND(ISNUMBER(_xlpm.q),_xlpm.q>0,ISNUMBER(_xlpm.u),_xlpm.u>0,ISNUMBER(_xlpm.d),_xlpm.d>=0,_xlpm.d<1), _xlpm.q*_xlpm.u*(1-_xlpm.d), "" ) ) ) -> 505.62 | K601: =_xlfn.LET( _xlpm.c,RawData!K601, _xlpm.r,RawData!J601, _xlpm.p,RawData!L601, IF(AND(ISNUMBER(_xlpm.c),_xlpm.c>=0),_xlpm.c, IF(AND(ISNUMBER(_xlpm.r),ISNUMBER(_xlpm.p)), _xlpm.r-_xlpm.p, "" ) ) ) -> 295.85 | L601: =_xlfn.LET( _xlpm.p,RawData!L601, _xlpm.r,RawData!J601, _xlpm.c,RawData!K601, IF(ISNUMBER(_xlpm.p),_xlpm.p, IF(AND(ISNUMBER(_xlpm.r),ISNUMBER(_xlpm.c)), _xlpm.r-_xlpm.c, "" ) )) -> 209.77

Sheet Pivot Tables
A2: Month | B2: Revenue | C2: Profit | D2: Quantity | G2: Product | H2: Revenue | I2: Profit | J2: Quantity
A3: Jan | B3: 39055.31 | C3: 11573.24 | D3: 234 | G3: Backpack | H3: 12490.01 | I3: 3770.32 | J3: 301 | M3: TOTAL REVENUE | N3: =SUM('Cleaned Data'!J:J) -> 550147.63
A4: Feb | B4: 50649.39 | C4: 15205.59 | D4: 245 | G4: Bookshelf | H4: 38807.75 | I4: 12063.43 | J4: 311
A5: Mar | B5: 42271.76 | C5: 14565.69 | D5: 309 | G5: Desk | H5: 71937.65 | I5: 23590.1 | J5: 312 | M5: TOTAL PROFIT | N5: =SUM('Cleaned Data'!L:L) -> 170681.87
A6: Apr | B6: 32866.91 | C6: 10530.11 | D6: 208 | G6: Headphones | H6: 18151.26 | I6: 5626.65 | J6: 257
A7: May | B7: 51113.15 | C7: 17244.26 | D7: 306 | G7: Keyboard | H7: 7340.97 | I7: 2072.48 | J7: 223 | M7: TOTAL ORDERS | N7: =COUNTA('Cleaned Data'!A2:A601) -> 600
A8: Jun | B8: 52638.04 | C8: 17364.91 | D8: 324 | G8: Laptop | H8: 120427.19 | I8: 37480.65 | J8: 167
A9: Jul | B9: 40547.8 | C9: 12028.68 | D9: 259 | G9: Monitor | H9: 45135.21 | I9: 13015.61 | J9: 233 | M9: TOTAL QUANTITY | N9: =SUM('Cleaned Data'!G:G) -> 3299
A10: Aug | B10: 59228.19 | C10: 19119.96 | D10: 325 | G10: Notebook | H10: 1888.28 | I10: 626.45 | J10: 262
A11: Sep | B11: 26034.69 | C11: 7531.51 | D11: 171 | G11: Office Chair | H11: 48177.19 | I11: 14304.71 | J11: 295 | M11: AVERAGE ORDER VALUE | N11: =SUM('Cleaned Data'!J:J)/COUNTA('Cleaned Data'!A:A) -> 915.38707
A12: Oct | B12: 38644.28 | C12: 10648.84 | D12: 268 | G12: Pen Set | H12: 3835.12 | I12: 1179.02 | J12: 357
A13: Nov | B13: 49210.94 | C13: 15007.72 | D13: 277 | G13: Printer | H13: 42026.92 | I13: 13705.77 | J13: 289
A14: Dec | B14: 67887.17 | C14: 19861.36 | D14: 373 | G14: Smartphone | H14: 139930.08 | I14: 43246.68 | J14: 292
A15: Grand Total | B15: 550147.63 | C15: 170681.87 | D15: 3299 | G15: Grand Total | H15: 550147.63 | I15: 170681.87 | J15: 3299
A19: Category | B19: Revenue | C19: Profit | D19: Quantity | G19: Region | H19: Revenue | I19: Profit | J19: Quantity
A20: Accessories | B20: 20353.39 | C20: 5993.4 | D20: 541 | G20: East | H20: 132965.32 | I20: 41887.86 | J20: 804
A21: Electronics | B21: 321080.06 | C21: 98426.59 | D21: 931 | G21: North | H21: 160955.49 | I21: 50127.24 | J21: 863
A22: Furniture | B22: 158768.49 | C22: 49927.43 | D22: 917 | G22: South | H22: 126451.47 | I22: 37974.37 | J22: 862
A23: Office Supplies | B23: 49945.69 | C23: 16334.45 | D23: 910 | G23: West | H23: 129775.35 | I23: 40692.4 | J23: 770
A24: Grand Total | B24: 550147.63 | C24: 170681.87 | D24: 3299 | G24: Grand Total | H24: 550147.63 | I24: 170681.87 | J24: 3299
A28: City | B28: Revenue | C28: Cost | D28: Quantity
A29: Ahmedabad | B29: 30510.68 | C29: 20493.41 | D29: 196
A30: Bengaluru | B30: 40456.5 | C30: 28780.63 | D30: 306
A31: Bhubaneswar | B31: 26447.79 | C31: 18548.75 | D31: 270
A32: Chennai | B32: 51346.6 | C32: 35645.41 | D32: 317
A33: Delhi | B33: 56346.78 | C33: 37692.1 | D33: 206
A34: Hyderabad | B34: 36909.03 | C34: 25341.97 | D34: 248
A35: Jaipur | B35: 44279.45 | C35: 31599.63 | D35: 265
A36: Kolkata | B36: 50792.03 | C36: 36382.33 | D36: 228
A37: Lucknow | B37: 60329.26 | C37: 41536.52 | D37: 392
A38: Mumbai | B38: 64880.75 | C38: 44963.37 | D38: 354
A39: Patna | B39: 55518.02 | C39: 36385.93 | D39: 306
A40: Pune | B40: 32330.74 | C40: 22095.71 | D40: 211
A41: Grand Total | B41: 550147.63 | C41: 379465.76 | D41: 3299

Sheet E-Commerce Sales Analysis
I1: E-Commerce Sales Analysis
